[
  {
    "img": "imgs/image80.jpg",
    "img_file": "image80.jpg",
    "total_exposure": 15147,
    "total_clicks": 358,
    "avg_ctr": 2.36,
    "max_ctr": 2.36,
    "min_ctr": 2.36,
    "invest_count": 1,
    "positions": [
      "商店轮播-定投200w"
    ],
    "types": [
      "静态+动态视频"
    ],
    "copies": [
      "真•开放世界生存对抗游戏\n预约领枪皮，抽京东卡、5070"
    ],
    "dates": [
      "2025-09-15"
    ],
    "date_range": [
      "2025-09-15",
      "2025-09-15"
    ],
    "category": "生存"
  },
  {
    "img": "imgs/image81.jpg",
    "img_file": "image81.jpg",
    "total_exposure": 14362,
    "total_clicks": 300,
    "avg_ctr": 2.09,
    "max_ctr": 2.09,
    "min_ctr": 2.09,
    "invest_count": 1,
    "positions": [
      "商店轮播-定投200w"
    ],
    "types": [
      "静态+动态视频"
    ],
    "copies": [
      "掠夺资源 荒岛称霸\n预约领枪皮，抽京东卡、5070"
    ],
    "dates": [
      "2025-09-15"
    ],
    "date_range": [
      "2025-09-15",
      "2025-09-15"
    ],
    "category": "对抗"
  },
  {
    "img": "imgs/image76.jpg",
    "img_file": "image76.jpg",
    "total_exposure": 243044,
    "total_clicks": 2250,
    "avg_ctr": 1.64,
    "max_ctr": 2.39,
    "min_ctr": 0.89,
    "invest_count": 2,
    "positions": [
      "商店轮播-定投200w",
      "商店轮播-全量"
    ],
    "types": [
      "静态+动态视频"
    ],
    "copies": [
      "搭建领地 攻防博弈\n预约领枪皮，抽京东卡、5070"
    ],
    "dates": [
      "2025-09-13",
      "2025-09-14"
    ],
    "date_range": [
      "2025-09-13",
      "2025-09-14"
    ],
    "category": "建造"
  },
  {
    "img": "imgs/image78.jpg",
    "img_file": "image78.jpg",
    "total_exposure": 21618,
    "total_clicks": 231,
    "avg_ctr": 1.575,
    "max_ctr": 2.59,
    "min_ctr": 0.56,
    "invest_count": 2,
    "positions": [
      "商店轮播-定投200w",
      "首帧轮播-定投100w"
    ],
    "types": [
      "静态+动态视频"
    ],
    "copies": [
      "荒岛求生 探索开放大世界\n预约领枪皮，抽京东卡、5070"
    ],
    "dates": [
      "2025-09-14",
      "2025-09-16"
    ],
    "date_range": [
      "2025-09-14",
      "2025-09-16"
    ],
    "category": "生存"
  },
  {
    "img": "imgs/image195.jpg",
    "img_file": "image195.jpg",
    "total_exposure": 50293,
    "total_clicks": 705,
    "avg_ctr": 1.4,
    "max_ctr": 1.4,
    "min_ctr": 1.4,
    "invest_count": 1,
    "positions": [
      "首帧轮播-定投100w"
    ],
    "types": [
      "静态"
    ],
    "copies": [
      "全网预约突破3200万\nRUST正版玩法授权"
    ],
    "dates": [
      "2026-04-03"
    ],
    "date_range": [
      "2026-04-03",
      "2026-04-03"
    ],
    "category": "趣味"
  },
  {
    "img": "imgs/image192.jpg",
    "img_file": "image192.jpg",
    "total_exposure": 543916,
    "total_clicks": 6757,
    "avg_ctr": 1.365,
    "max_ctr": 1.6838,
    "min_ctr": 1.0462,
    "invest_count": 2,
    "positions": [
      "商店轮播-全量"
    ],
    "types": [
      "静态"
    ],
    "copies": [
      "这座基地，是我的杰作\nRUST正版授权生存对抗游戏",
      "建造你的专属基地\nRUST正版授权生存对抗游戏"
    ],
    "dates": [
      "2026-03-26",
      "2026-04-04"
    ],
    "date_range": [
      "2026-03-26",
      "2026-04-04"
    ],
    "category": "建造"
  },
  {
    "img": "imgs/image187.jpg",
    "img_file": "image187.jpg",
    "total_exposure": 632288,
    "total_clicks": 7675,
    "avg_ctr": 1.3367,
    "max_ctr": 1.72,
    "min_ctr": 0.94,
    "invest_count": 4,
    "positions": [
      "商店轮播-全量",
      "商店轮播-定投200w",
      "首帧轮播-定投100w"
    ],
    "types": [
      "静态+动态视频",
      "静态"
    ],
    "copies": [
      "开放世界，射击生存对抗\n预约赢5070Ti、千元Q币",
      "RUST正版玩法授权\n开放世界，射击生存对抗"
    ],
    "dates": [
      "2026-03-09",
      "2026-03-12",
      "2026-03-22",
      "2026-03-26"
    ],
    "date_range": [
      "2026-03-09",
      "2026-03-26"
    ],
    "category": "对抗"
  },
  {
    "img": "imgs/image189.jpg",
    "img_file": "image189.jpg",
    "total_exposure": 1880989,
    "total_clicks": 21762,
    "avg_ctr": 1.2684,
    "max_ctr": 1.8163,
    "min_ctr": 1.0329,
    "invest_count": 6,
    "positions": [
      "商店轮播-全量",
      "首帧轮播-定投100w"
    ],
    "types": [
      "静态"
    ],
    "copies": [
      "从零开始，独狼也能翻盘！\n没见过这么野的生存对抗游戏"
    ],
    "dates": [
      "2026-03-22",
      "2026-03-24",
      "2026-03-26",
      "2026-04-03",
      "2026-04-04",
      "2026-04-06"
    ],
    "date_range": [
      "2026-03-22",
      "2026-04-06"
    ],
    "category": "生存"
  },
  {
    "img": "imgs/image191.jpg",
    "img_file": "image191.jpg",
    "total_exposure": 585346,
    "total_clicks": 6351,
    "avg_ctr": 1.2542,
    "max_ctr": 1.6411,
    "min_ctr": 0.8674,
    "invest_count": 2,
    "positions": [
      "商店轮播-全量"
    ],
    "types": [
      "静态"
    ],
    "copies": [
      "陆地追不上？那就上天\n高自由度生存对抗玩到爽"
    ],
    "dates": [
      "2026-03-26",
      "2026-04-06"
    ],
    "date_range": [
      "2026-03-26",
      "2026-04-06"
    ],
    "category": "对抗"
  },
  {
    "img": "imgs/image21.jpg",
    "img_file": "image21.jpg",
    "total_exposure": 437979,
    "total_clicks": 2580,
    "avg_ctr": 1.2347,
    "max_ctr": 2.49,
    "min_ctr": 0.42,
    "invest_count": 3,
    "positions": [
      "商店轮播-全量",
      "首帧轮播-定投100w"
    ],
    "types": [
      "静态+动态视频",
      "静态"
    ],
    "copies": [
      "RUST正版玩法授权\n9月19日登岛测试，立即报名！",
      "RUST正版玩法授权\n9月大规模测试，PC抢先招募中"
    ],
    "dates": [
      "2025-08-04",
      "2025-08-06",
      "2025-08-11"
    ],
    "date_range": [
      "2025-08-04",
      "2025-08-11"
    ],
    "category": "建造"
  },
  {
    "img": "imgs/image6.jpg",
    "img_file": "image6.jpg",
    "total_exposure": 609949,
    "total_clicks": 5778,
    "avg_ctr": 1.137,
    "max_ctr": 2.08,
    "min_ctr": 0.7978,
    "invest_count": 5,
    "positions": [
      "商店轮播-全量",
      "商店轮播-定投200w",
      "首帧轮播-定投100w"
    ],
    "types": [
      "静态+动态视频",
      "静态"
    ],
    "copies": [
      "全球顶流生存对抗游戏9月测试\\nPC抢先招募，预约领限定枪皮",
      "标题：全球顶流生存对抗游戏\n副标：立即预约！领限定枪皮抽5070",
      "RUST正版玩法授权\n9月19日登岛测试，立即报名！",
      "RUST正版玩法授权\n9月大规模测试，PC抢先招募中",
      "全球顶流生存对抗游戏9月测试\nPC抢先招募，预约领限定枪皮"
    ],
    "dates": [
      "2025-07-05",
      "2025-07-12",
      "2025-07-15",
      "2025-08-06",
      "2025-08-11"
    ],
    "date_range": [
      "2025-07-05",
      "2025-08-11"
    ],
    "category": "福利"
  },
  {
    "img": "imgs/image175.jpg",
    "img_file": "image175.jpg",
    "total_exposure": 4308258,
    "total_clicks": 42604,
    "avg_ctr": 1.1352,
    "max_ctr": 1.83,
    "min_ctr": 0.7858,
    "invest_count": 14,
    "positions": [
      "首帧轮播-全量",
      "商店轮播-定投200w",
      "商店轮播-全量",
      "首帧轮播-定投100w"
    ],
    "types": [
      "静态+动态视频",
      "静态"
    ],
    "copies": [
      "没见过这么野的生存对抗游戏\n测试火热进行中，预约赢Q币",
      "预约赢5070显卡、千元Q币\nRUST正版玩法授权",
      "开放世界，射击生存对抗\n预约赢5070Ti、千元Q币",
      "没见过这么野的生存对抗游戏\n立即参与测试，赢千元Q币",
      "RUST正版玩法授权\n全新体验，沉浸式生存对抗！",
      "立即抢号，参与终极测试！\n赢5070Ti显卡、千元Q币"
    ],
    "dates": [
      "2026-02-27",
      "2026-03-03",
      "2026-03-07",
      "2026-03-08",
      "2026-03-09",
      "2026-03-11",
      "2026-03-12",
      "2026-03-17",
      "2026-03-22",
      "2026-03-24",
      "2026-03-26",
      "2026-04-03",
      "2026-04-04",
      "2026-04-06"
    ],
    "date_range": [
      "2026-02-27",
      "2026-04-06"
    ],
    "category": "探索"
  },
  {
    "img": "imgs/image15.png",
    "img_file": "image15.png",
    "total_exposure": 903653,
    "total_clicks": 8672,
    "avg_ctr": 0.96,
    "max_ctr": 1.11,
    "min_ctr": 1.11,
    "invest_count": 2,
    "positions": [
      "商店轮播-全量"
    ],
    "types": [
      "静态",
      "静态+动态视频"
    ],
    "copies": [
      "全球顶流生存对抗游戏9月测试\nPC抢先招募，预约赢5070",
      "真•开放世界生存对抗游戏\n预约领枪皮，抽京东卡、5070"
    ],
    "dates": [
      "2025-07-23",
      "2025-09-07"
    ],
    "date_range": [
      "2025-07-23",
      "2025-09-07"
    ],
    "category": "福利"
  },
  {
    "img": "imgs/image79.jpg",
    "img_file": "image79.jpg",
    "total_exposure": 465259,
    "total_clicks": 2973,
    "avg_ctr": 1.08,
    "max_ctr": 2.64,
    "min_ctr": 0.47,
    "invest_count": 4,
    "positions": [
      "商店轮播-全量",
      "商店轮播-定投200w",
      "首帧轮播-定投100w"
    ],
    "types": [
      "静态+动态视频"
    ],
    "copies": [
      "掠夺资源 荒岛称霸\n预约领枪皮，抽京东卡、5070"
    ],
    "dates": [
      "2025-09-14",
      "2025-09-16",
      "2025-09-19",
      "2025-09-20"
    ],
    "date_range": [
      "2025-09-14",
      "2025-09-20"
    ],
    "category": "对抗"
  },
  {
    "img": "imgs/image194.jpg",
    "img_file": "image194.jpg",
    "total_exposure": 483821,
    "total_clicks": 4629,
    "avg_ctr": 1.0781,
    "max_ctr": 1.23,
    "min_ctr": 0.9261,
    "invest_count": 2,
    "positions": [
      "商店轮播-全量",
      "首帧轮播-定投100w"
    ],
    "types": [
      "静态"
    ],
    "copies": [
      "这次，拿回属于我的一切！\n没见过这么野的生存对抗游戏",
      "这次，拿回属于我的一切！\nRUST正版授权生存对抗游戏"
    ],
    "dates": [
      "2026-04-03",
      "2026-04-06"
    ],
    "date_range": [
      "2026-04-03",
      "2026-04-06"
    ],
    "category": "对抗"
  },
  {
    "img": "imgs/image9.jpg",
    "img_file": "image9.jpg",
    "total_exposure": 490088,
    "total_clicks": 4130,
    "avg_ctr": 1.07,
    "max_ctr": 1.61,
    "min_ctr": 0.75,
    "invest_count": 3,
    "positions": [
      "商店轮播-全量",
      "首帧轮播-定投100w"
    ],
    "types": [
      "静态"
    ],
    "copies": [
      "RUST正版玩法授权\n9月19日登岛测试，立即报名！",
      "RUST正版玩法授权\n9月大规模测试 PC抢先招募中"
    ],
    "dates": [
      "2025-07-12",
      "2025-07-15",
      "2025-08-11"
    ],
    "date_range": [
      "2025-07-12",
      "2025-08-11"
    ],
    "category": "福利"
  },
  {
    "img": "imgs/image106.jpg",
    "img_file": "image106.jpg",
    "total_exposure": 7134,
    "total_clicks": 76,
    "avg_ctr": 1.07,
    "max_ctr": 1.07,
    "min_ctr": 1.07,
    "invest_count": 1,
    "positions": [
      "商店轮播-定投200w"
    ],
    "types": [
      "静态+动态视频"
    ],
    "copies": [
      "没见过这么野的生存对抗游戏\n预约领限定枪皮、千元Q币"
    ],
    "dates": [
      "2025-10-18"
    ],
    "date_range": [
      "2025-10-18",
      "2025-10-18"
    ],
    "category": "趣味"
  },
  {
    "img": "imgs/image107.jpg",
    "img_file": "image107.jpg",
    "total_exposure": 7095,
    "total_clicks": 75,
    "avg_ctr": 1.06,
    "max_ctr": 1.06,
    "min_ctr": 1.06,
    "invest_count": 1,
    "positions": [
      "商店轮播-定投200w"
    ],
    "types": [
      "静态+动态视频"
    ],
    "copies": [
      "开放世界 生存对抗\n预约领枪皮，暴击千元Q币！"
    ],
    "dates": [
      "2025-10-18"
    ],
    "date_range": [
      "2025-10-18",
      "2025-10-18"
    ],
    "category": "探索"
  },
  {
    "img": "imgs/image193.jpg",
    "img_file": "image193.jpg",
    "total_exposure": 399887,
    "total_clicks": 3704,
    "avg_ctr": 1.032,
    "max_ctr": 1.17,
    "min_ctr": 0.894,
    "invest_count": 2,
    "positions": [
      "商店轮播-全量",
      "首帧轮播-定投100w"
    ],
    "types": [
      "静态"
    ],
    "copies": [
      "物资争夺战，谁敢来拿？\n没见过这么野的生存对抗游戏"
    ],
    "dates": [
      "2026-04-03",
      "2026-04-04"
    ],
    "date_range": [
      "2026-04-03",
      "2026-04-04"
    ],
    "category": "对抗"
  },
  {
    "img": "imgs/image46.png",
    "img_file": "image46.png",
    "total_exposure": 4767883,
    "total_clicks": 41552,
    "avg_ctr": 1.0183,
    "max_ctr": 2.5097,
    "min_ctr": 0.52,
    "invest_count": 17,
    "positions": [
      "首帧轮播-全量",
      "商店轮播-全量",
      "商店轮播-定投200w",
      "首帧轮播-定投100w"
    ],
    "types": [
      "静态+动态视频",
      "静态"
    ],
    "copies": [
      "活下来！然后成为别人的恶梦​\n9月19日登岛测试，立即报名！",
      "活下来！然后成为别人的恶梦​\n预约领枪皮，抽京东卡、5070",
      "活下来！然后成为别人的恶梦​\n预约有礼，点击报名9月登岛测试",
      "RUST玩法授权，领预约豪礼\n9月19日登岛测试，立即报名！",
      "活下来！然后成为别人的恶梦​\n登岛测试，立即报名！",
      "开放世界 生存对抗\n预约领枪皮，抽京东卡、5070",
      "全网两千万预约达成！\n预约领枪皮，抽京东卡、5070",
      "活下来！然后成为别人的恶梦​\n9月登岛测试，立即报名！"
    ],
    "dates": [
      "2025-08-22",
      "2025-08-24",
      "2025-08-29",
      "2025-08-30",
      "2025-09-03",
      "2025-09-04",
      "2025-09-06",
      "2025-09-07",
      "2025-09-09",
      "2025-09-13",
      "2025-09-14",
      "2025-09-15",
      "2025-09-19",
      "2025-09-20",
      "2025-09-21",
      "2025-09-22"
    ],
    "date_range": [
      "2025-08-22",
      "2025-09-22"
    ],
    "category": "趣味"
  },
  {
    "img": "imgs/image75.jpg",
    "img_file": "image75.jpg",
    "total_exposure": 1183861,
    "total_clicks": 8517,
    "avg_ctr": 1.0029,
    "max_ctr": 2.85,
    "min_ctr": 0.55,
    "invest_count": 7,
    "positions": [
      "商店轮播-定投200w",
      "商店轮播-全量",
      "首帧轮播-定投100w"
    ],
    "types": [
      "静态+动态视频"
    ],
    "copies": [
      "生存试炼，活到最后才是赢家！\n预约领枪皮，抽京东卡、5070"
    ],
    "dates": [
      "2025-09-13",
      "2025-09-14",
      "2025-09-16",
      "2025-09-19",
      "2025-09-20",
      "2025-09-21",
      "2025-09-22"
    ],
    "date_range": [
      "2025-09-13",
      "2025-09-22"
    ],
    "category": "生存"
  },
  {
    "img": "imgs/image110.jpg",
    "img_file": "image110.jpg",
    "total_exposure": 429472,
    "total_clicks": 4281,
    "avg_ctr": 0.9968,
    "max_ctr": 0.9968,
    "min_ctr": 0.9968,
    "invest_count": 1,
    "positions": [
      "商店轮播-全量"
    ],
    "types": [
      "静态+动态视频"
    ],
    "copies": [
      "没见过这么野的生存对抗游戏\n预约领限定枪皮、千元Q币"
    ],
    "dates": [
      "2025-10-21"
    ],
    "date_range": [
      "2025-10-21",
      "2025-10-21"
    ],
    "category": "趣味"
  },
  {
    "img": "imgs/image108.jpg",
    "img_file": "image108.jpg",
    "total_exposure": 425652,
    "total_clicks": 4214,
    "avg_ctr": 0.99,
    "max_ctr": 0.99,
    "min_ctr": 0.99,
    "invest_count": 1,
    "positions": [
      "商店轮播-全量"
    ],
    "types": [
      "静态+动态视频"
    ],
    "copies": [
      "生存试炼，活到最后才是赢家！\n预约领枪皮，暴击千元Q币！"
    ],
    "dates": [
      "2025-10-21"
    ],
    "date_range": [
      "2025-10-21",
      "2025-10-21"
    ],
    "category": "生存"
  },
  {
    "img": "imgs/image44.png",
    "img_file": "image44.png",
    "total_exposure": 7376370,
    "total_clicks": 63013,
    "avg_ctr": 0.978,
    "max_ctr": 2.7732,
    "min_ctr": 0.52,
    "invest_count": 24,
    "positions": [
      "首帧轮播-全量",
      "商店轮播-全量",
      "商店轮播-定投200w",
      "首帧轮播-定投100w"
    ],
    "types": [
      "静态+动态视频",
      "静态"
    ],
    "copies": [
      "荒岛求生 探索开放大世界\n收集情报领最高188Q币",
      "荒岛求生 探索开放大世界\n预约领枪皮，抽京东卡、5070",
      "荒岛求生 探索开放大世界\n9月登岛测试，立即报名！",
      "开放世界 自由驰骋\n收集情报领最高188Q币！",
      "RUST玩法授权，领预约豪礼\n9月19日登岛测试，立即报名！",
      "荒岛求生 探索开放大世界\n预约领限定枪皮，抽5070",
      "荒岛求生 探索开放大世界\n收集情报领最高188Q币！"
    ],
    "dates": [
      "2025-08-22",
      "2025-09-03",
      "2025-09-04",
      "2025-09-06",
      "2025-09-07",
      "2025-09-09",
      "2025-09-13",
      "2025-09-14",
      "2025-09-15",
      "2025-09-16",
      "2025-09-21",
      "2025-09-22",
      "2025-09-23",
      "2025-09-25",
      "2025-09-26",
      "2025-09-27",
      "2025-09-28",
      "2025-10-02",
      "2025-10-03",
      "2025-10-04",
      "2025-10-05",
      "2025-10-06",
      "2025-10-09"
    ],
    "date_range": [
      "2025-08-22",
      "2025-10-09"
    ],
    "category": "探索"
  },
  {
    "img": "imgs/image57.jpg",
    "img_file": "image57.jpg",
    "total_exposure": 8102306,
    "total_clicks": 69735,
    "avg_ctr": 0.9733,
    "max_ctr": 2.6272,
    "min_ctr": 0.59,
    "invest_count": 26,
    "positions": [
      "首帧轮播-全量",
      "商店轮播-全量",
      "商店轮播-定投200w",
      "首帧轮播-定投100w"
    ],
    "types": [
      "静态+动态视频",
      "静态"
    ],
    "copies": [
      "这次你当猎物还是猎人？\n预约领枪皮，抽京东卡、5070",
      "开放世界生存对抗游戏\n9月登岛测试，立即报名！",
      "开放世界生存对抗【搜打拆】\n9月登岛测试，立即报名！",
      "开放世界生存对抗游戏\n预约领枪皮，抽京东卡、5070",
      "开放世界，生存对抗【搜打拆】\n登岛测试，立即报名！",
      "真•开放世界生存对抗游戏\n预约领枪皮，抽京东卡、5070",
      "这次你当猎物还是猎人？\n预约领枪皮，暴击千元Q币"
    ],
    "dates": [
      "2025-08-30",
      "2025-09-03",
      "2025-09-04",
      "2025-09-06",
      "2025-09-07",
      "2025-09-09",
      "2025-09-13",
      "2025-09-14",
      "2025-09-15",
      "2025-09-16",
      "2025-09-19",
      "2025-09-20",
      "2025-09-21",
      "2025-09-22",
      "2025-09-23",
      "2025-09-25",
      "2025-09-26",
      "2025-09-27",
      "2025-09-28",
      "2025-10-02",
      "2025-10-03",
      "2025-10-04",
      "2025-10-05",
      "2025-10-06",
      "2025-10-09"
    ],
    "date_range": [
      "2025-08-30",
      "2025-10-09"
    ],
    "category": "对抗"
  },
  {
    "img": "imgs/image28.png",
    "img_file": "image28.png",
    "total_exposure": 2555608,
    "total_clicks": 19188,
    "avg_ctr": 0.751,
    "max_ctr": 2.32,
    "min_ctr": 0.44,
    "invest_count": 10,
    "positions": [
      "商店轮播-全量",
      "首帧轮播-定投100w"
    ],
    "types": [
      "静态+动态视频",
      "静态"
    ],
    "copies": [
      "丛林法则生存试炼，预约领枪皮\n9月19日登岛测试，立即报名！",
      "全球顶流生存对抗游戏9月测试\nPC抢先招募，预约赢5070",
      "丛林法则 生存试炼\n预约领限定枪皮，抽5070",
      "RUST正版玩法授权\n9月19日登岛测试，立即报名！",
      "RUST正版玩法授权\n9月大规模测试，PC抢先招募中",
      "RUST玩法授权，领预约豪礼\n9月19日登岛测试，立即报名！",
      "9月登岛测试，立即报名！\nRUST玩法授权，领预约豪礼"
    ],
    "dates": [
      "2025-08-04",
      "2025-08-06",
      "2025-08-09",
      "2025-08-11",
      "2025-08-24",
      "2025-08-29",
      "2025-08-30",
      "2025-08-16",
      "2025-08-22",
      "2025-08-13"
    ],
    "date_range": [
      "2025-08-04",
      "2025-08-30"
    ],
    "category": "生存"
  },
  {
    "img": "imgs/image77.jpg",
    "img_file": "image77.jpg",
    "total_exposure": 4495998,
    "total_clicks": 36315,
    "avg_ctr": 0.9646,
    "max_ctr": 2.5,
    "min_ctr": 0.6041,
    "invest_count": 13,
    "positions": [
      "首帧轮播-全量",
      "商店轮播-定投200w",
      "商店轮播-全量",
      "首帧轮播-定投100w"
    ],
    "types": [
      "静态+动态视频"
    ],
    "copies": [
      "开放世界生存对抗，来制霸荒岛\n预约领枪皮，抽京东卡、5070",
      "开放世界生存对抗，制霸荒岛\n预约领限定枪皮、千元Q币",
      "真•开放世界生存对抗游戏\n预约领枪皮，抽京东卡、5070",
      "没见过这么野的生存对抗游戏\n预约领枪皮，抽京东卡、5070"
    ],
    "dates": [
      "2025-09-13",
      "2025-09-14",
      "2025-09-23",
      "2025-09-25",
      "2025-09-26",
      "2025-09-27",
      "2025-09-28",
      "2025-10-02",
      "2025-10-03",
      "2025-10-04",
      "2025-10-05",
      "2025-10-06",
      "2025-10-09"
    ],
    "date_range": [
      "2025-09-13",
      "2025-10-09"
    ],
    "category": "对抗"
  },
  {
    "img": "imgs/image197.jpg",
    "img_file": "image197.jpg",
    "total_exposure": 429498,
    "total_clicks": 4130,
    "avg_ctr": 0.9616,
    "max_ctr": 0.9616,
    "min_ctr": 0.9616,
    "invest_count": 1,
    "positions": [
      "商店轮播-全量"
    ],
    "types": [
      "静态"
    ],
    "copies": [
      "RUST正版玩法授权\n开放世界，射击生存对抗"
    ],
    "dates": [
      "2026-04-06"
    ],
    "date_range": [
      "2026-04-06",
      "2026-04-06"
    ],
    "category": "福利"
  },
  {
    "img": "imgs/image18.jpg",
    "img_file": "image18.jpg",
    "total_exposure": 864491,
    "total_clicks": 8278,
    "avg_ctr": 0.96,
    "max_ctr": 0.96,
    "min_ctr": 0.96,
    "invest_count": 1,
    "positions": [
      "商店轮播-全量"
    ],
    "types": [
      "静态"
    ],
    "copies": [
      "全球顶流生存对抗游戏9月测试\nPC抢先招募，预约赢5070"
    ],
    "dates": [
      "2025-07-25"
    ],
    "date_range": [
      "2025-07-25",
      "2025-07-25"
    ],
    "category": "福利"
  },
  {
    "img": "imgs/image173.jpg",
    "img_file": "image173.jpg",
    "total_exposure": 2081,
    "total_clicks": 20,
    "avg_ctr": 0.96,
    "max_ctr": 0.96,
    "min_ctr": 0.96,
    "invest_count": 1,
    "positions": [
      "商店轮播-定投200w"
    ],
    "types": [
      "静态"
    ],
    "copies": [
      "立即抢号，参与终极测试\n高自由度生存对抗玩到爽！"
    ],
    "dates": [
      "2026-02-14"
    ],
    "date_range": [
      "2026-02-14",
      "2026-02-14"
    ],
    "category": "对抗"
  },
  {
    "img": "imgs/image183.jpg",
    "img_file": "image183.jpg",
    "total_exposure": 1074824,
    "total_clicks": 9414,
    "avg_ctr": 0.9494,
    "max_ctr": 1.12,
    "min_ctr": 0.7973,
    "invest_count": 4,
    "positions": [
      "商店轮播-全量",
      "商店轮播-定投200w"
    ],
    "types": [
      "静态+动态视频",
      "静态"
    ],
    "copies": [
      "全新体验，沉浸式生存对抗！\n终极测试开放中，点击立即抢号",
      "全新体验，沉浸式生存对抗！\n预约赢5070Ti、千元Q币",
      "RUST正版玩法授权\n开放世界，射击生存对抗"
    ],
    "dates": [
      "2026-03-07",
      "2026-03-11",
      "2026-03-17",
      "2026-03-24"
    ],
    "date_range": [
      "2026-03-07",
      "2026-03-24"
    ],
    "category": "对抗"
  },
  {
    "img": "imgs/image161.jpg",
    "img_file": "image161.jpg",
    "total_exposure": 2898096,
    "total_clicks": 24178,
    "avg_ctr": 0.9444,
    "max_ctr": 1.5,
    "min_ctr": 0.7354,
    "invest_count": 8,
    "positions": [
      "首帧轮播-全量",
      "商店轮播-全量",
      "首帧轮播-定投100w"
    ],
    "types": [
      "静态+动态视频",
      "静态"
    ],
    "copies": [
      "全新体验，沉浸式生存对抗！\n终极测试开放中，点击立即抢号",
      "生存对抗，搭建你的专属领地\n立即抢号，参与终极测试！"
    ],
    "dates": [
      "2026-02-04",
      "2026-02-07",
      "2026-02-27",
      "2026-03-03",
      "2026-03-08",
      "2026-03-11",
      "2026-03-12",
      "2026-03-17"
    ],
    "date_range": [
      "2026-02-04",
      "2026-03-17"
    ],
    "category": "建造"
  },
  {
    "img": "imgs/image17.jpg",
    "img_file": "image17.jpg",
    "total_exposure": 1245135,
    "total_clicks": 10254,
    "avg_ctr": 0.824,
    "max_ctr": 1.16,
    "min_ctr": 0.72,
    "invest_count": 3,
    "positions": [
      "商店轮播-全量"
    ],
    "types": [
      "静态+动态视频",
      "静态"
    ],
    "copies": [
      "搭建领地 攻防博弈\n9月登岛测试，立即报名！",
      "RUST正版玩法授权\n9月大规模测试，PC抢先招募中",
      "全球顶流生存对抗游戏9月测试\nPC抢先招募，预约赢5070"
    ],
    "dates": [
      "2025-07-23",
      "2025-09-07",
      "2025-08-04"
    ],
    "date_range": [
      "2025-07-23",
      "2025-09-07"
    ],
    "category": "建造"
  },
  {
    "img": "imgs/image190.jpg",
    "img_file": "image190.jpg",
    "total_exposure": 690367,
    "total_clicks": 6458,
    "avg_ctr": 0.9336,
    "max_ctr": 0.972,
    "min_ctr": 0.8953,
    "invest_count": 2,
    "positions": [
      "商店轮播-全量"
    ],
    "types": [
      "静态"
    ],
    "copies": [
      "老六偷家？玩法由你定！\n没见过这么野的生存对抗游戏",
      "老六偷家？玩法由你定！\nRUST正版授权生存对抗游戏"
    ],
    "dates": [
      "2026-03-24",
      "2026-04-04"
    ],
    "date_range": [
      "2026-03-24",
      "2026-04-04"
    ],
    "category": "趣味"
  },
  {
    "img": "imgs/image162.jpg",
    "img_file": "image162.jpg",
    "total_exposure": 192139,
    "total_clicks": 1787,
    "avg_ctr": 0.9301,
    "max_ctr": 0.9301,
    "min_ctr": 0.9301,
    "invest_count": 1,
    "positions": [
      "商店轮播-全量"
    ],
    "types": [
      "静态"
    ],
    "copies": [
      "生存对抗，搭建你的专属领地\n立即抢号，参与终极测试！"
    ],
    "dates": [
      "2026-02-05"
    ],
    "date_range": [
      "2026-02-05",
      "2026-02-05"
    ],
    "category": "建造"
  },
  {
    "img": "imgs/image196.jpg",
    "img_file": "image196.jpg",
    "total_exposure": 354062,
    "total_clicks": 3276,
    "avg_ctr": 0.9253,
    "max_ctr": 0.9253,
    "min_ctr": 0.9253,
    "invest_count": 1,
    "positions": [
      "商店轮播-全量"
    ],
    "types": [
      "静态"
    ],
    "copies": [
      "预约赢50系显卡、千元Q币\nRUST正版授权生存对抗游戏"
    ],
    "dates": [
      "2026-04-04"
    ],
    "date_range": [
      "2026-04-04",
      "2026-04-04"
    ],
    "category": "福利"
  },
  {
    "img": "imgs/image11.jpg",
    "img_file": "image11.jpg",
    "total_exposure": 12346925,
    "total_clicks": 104822,
    "avg_ctr": 0.849,
    "max_ctr": 2.2396,
    "min_ctr": 0.45,
    "invest_count": 37,
    "positions": [
      "首帧轮播-全量",
      "商店轮播-全量",
      "商店轮播-定投200w",
      "首帧轮播-定投100w"
    ],
    "types": [
      "静态+动态视频",
      "静态"
    ],
    "copies": [
      "全球顶流生存对抗游戏9月测试\nPC抢先招募，预约赢5070",
      "RUST正版玩法授权\n9月19日登岛测试，立即报名！",
      "开放世界生存对抗【搜打拆】\n预约领限定枪皮，抽5070",
      "真•开放世界生存对抗游戏\n9月登岛测试，立即报名！",
      "全网预约突破2000万\n收集情报领最高188Q币！",
      "RUST正版玩法授权\n9月大规模测试，PC抢先招募中",
      "9月登岛测试，立即报名！\nRUST玩法授权，领预约豪礼",
      "RUST玩法授权，领预约豪礼\n9月19日登岛测试，立即报名！",
      "标题：全球顶流生存对抗游戏\n副标：立即预约 随我一起上岛！",
      "开放世界 生存对抗\n预约领枪皮，抽京东卡、5070",
      "开放世界 生存对抗\n收集情报领最高188Q币！",
      "全网两千万预约达成！\n预约领枪皮，抽京东卡、5070",
      "开放世界 生存对抗\n收集情报领最高188Q币",
      "全球顶流生存对抗游戏9月测试\n抢先招募，预约领限定枪皮",
      "真•开放世界生存对抗游戏\n预约领枪皮，抽京东卡、5070",
      "全球顶流生存对抗游戏9月测试\nPC抢先招募，预约领限定枪皮",
      "真·开放世界，顶流生存对抗\n预约领限定枪皮，抽5070",
      "真·开放世界，顶流生存射击\n9月19日登岛测试，立即报名！"
    ],
    "dates": [
      "2025-07-05",
      "2025-07-12",
      "2025-07-15",
      "2025-07-19",
      "2025-07-23",
      "2025-07-25",
      "2025-08-09",
      "2025-08-16",
      "2025-08-22",
      "2025-09-03",
      "2025-09-04",
      "2025-09-06",
      "2025-09-07",
      "2025-09-09",
      "2025-09-13",
      "2025-09-14",
      "2025-09-15",
      "2025-09-16",
      "2025-09-19",
      "2025-09-20",
      "2025-09-21",
      "2025-09-22",
      "2025-09-23",
      "2025-09-25",
      "2025-09-26",
      "2025-09-27",
      "2025-09-28",
      "2025-10-02",
      "2025-10-03",
      "2025-10-04",
      "2025-10-05",
      "2025-10-06",
      "2025-10-09",
      "2025-08-24",
      "2025-08-29",
      "2025-08-30",
      "2025-08-13"
    ],
    "date_range": [
      "2025-07-05",
      "2025-10-09"
    ],
    "category": "福利"
  },
  {
    "img": "imgs/image188.jpg",
    "img_file": "image188.jpg",
    "total_exposure": 733608,
    "total_clicks": 6590,
    "avg_ctr": 0.9018,
    "max_ctr": 0.9409,
    "min_ctr": 0.8626,
    "invest_count": 2,
    "positions": [
      "商店轮播-全量"
    ],
    "types": [
      "静态"
    ],
    "copies": [
      "今晚，拿下这座基地！\nRUST正版授权生存对抗游戏"
    ],
    "dates": [
      "2026-03-22",
      "2026-03-24"
    ],
    "date_range": [
      "2026-03-22",
      "2026-03-24"
    ],
    "category": "对抗"
  },
  {
    "img": "imgs/image5.jpg",
    "img_file": "image5.jpg",
    "total_exposure": 499295,
    "total_clicks": 4420,
    "avg_ctr": 0.8998,
    "max_ctr": 0.94,
    "min_ctr": 0.82,
    "invest_count": 3,
    "positions": [
      "商店轮播-全量",
      "商店轮播-定投200w"
    ],
    "types": [
      "静态"
    ],
    "copies": [
      "全球顶流生存对抗游戏9月测试\nPC抢先招募，预约领限定枪皮",
      "标题：全球顶流生存对抗游戏\n副标：立即预约！领限定枪皮抽5070"
    ],
    "dates": [
      "2025-07-05",
      "2025-07-12",
      "2025-07-15"
    ],
    "date_range": [
      "2025-07-05",
      "2025-07-15"
    ],
    "category": "福利"
  },
  {
    "img": "imgs/image100.jpg",
    "img_file": "image100.jpg",
    "total_exposure": 2283338,
    "total_clicks": 21760,
    "avg_ctr": 0.8961,
    "max_ctr": 1.12,
    "min_ctr": 0.63,
    "invest_count": 9,
    "positions": [
      "商店轮播-定投200w",
      "商店轮播-全量",
      "首帧轮播-定投100w"
    ],
    "types": [
      "静态+动态视频"
    ],
    "copies": [
      "48小时直播，即将开启\n来抢号试玩，预约领Q币！",
      "没见过这么野的生存对抗游戏\n预约领限定枪皮、暴击千元Q币",
      "48小时直播，即将开启\n来抢号试玩，预约领Q币",
      "没见过这么野的生存对抗游戏\n预约领限定枪皮、千元Q币",
      "48小时直播，今日开启\n点击抢号试玩，预约领Q币",
      "没见过这么野的生存对抗游戏\n点击抢号试玩，预约领Q币"
    ],
    "dates": [
      "2025-10-06",
      "2025-10-09",
      "2025-10-10",
      "2025-10-11",
      "2025-10-12",
      "2025-10-14",
      "2025-10-17",
      "2025-10-18",
      "2025-10-21"
    ],
    "date_range": [
      "2025-10-06",
      "2025-10-21"
    ],
    "category": "福利"
  },
  {
    "img": "imgs/image60.jpg",
    "img_file": "image60.jpg",
    "total_exposure": 389810,
    "total_clicks": 3422,
    "avg_ctr": 0.88,
    "max_ctr": 0.88,
    "min_ctr": 0.88,
    "invest_count": 1,
    "positions": [
      "商店轮播-全量"
    ],
    "types": [
      "静态"
    ],
    "copies": [
      "这次你当猎物还是猎人？\n9月登岛测试，立即报名！"
    ],
    "dates": [
      "2025-09-03"
    ],
    "date_range": [
      "2025-09-03",
      "2025-09-03"
    ],
    "category": "对抗"
  },
  {
    "img": "imgs/image105.jpg",
    "img_file": "image105.jpg",
    "total_exposure": 21908,
    "total_clicks": 194,
    "avg_ctr": 0.88,
    "max_ctr": 0.92,
    "min_ctr": 0.84,
    "invest_count": 2,
    "positions": [
      "商店轮播-定投200w"
    ],
    "types": [
      "静态+动态视频"
    ],
    "copies": [
      "没见过这么野的生存对抗游戏\n预约领限定枪皮、千元Q币"
    ],
    "dates": [
      "2025-10-17",
      "2025-10-27"
    ],
    "date_range": [
      "2025-10-17",
      "2025-10-27"
    ],
    "category": "趣味"
  },
  {
    "img": "imgs/image160.jpg",
    "img_file": "image160.jpg",
    "total_exposure": 1730303,
    "total_clicks": 13523,
    "avg_ctr": 0.88,
    "max_ctr": 1.0094,
    "min_ctr": 0.6952,
    "invest_count": 3,
    "positions": [
      "首帧轮播-全量",
      "商店轮播-全量"
    ],
    "types": [
      "静态+动态视频",
      "静态"
    ],
    "copies": [
      "高自由度生存对抗玩到爽\n分享测试资格，邀友一起上岛！",
      "没见过这么野的生存对抗游戏！\n终极测试开放中，点击立即抢号",
      "终极测试 火热开启\n立即抢号，抢先一步登岛"
    ],
    "dates": [
      "2026-02-04",
      "2026-02-07",
      "2026-02-13"
    ],
    "date_range": [
      "2026-02-04",
      "2026-02-13"
    ],
    "category": "对抗"
  },
  {
    "img": "imgs/image198.jpg",
    "img_file": "image198.jpg",
    "total_exposure": 422624,
    "total_clicks": 3717,
    "avg_ctr": 0.8795,
    "max_ctr": 0.8795,
    "min_ctr": 0.8795,
    "invest_count": 1,
    "positions": [
      "商店轮播-全量"
    ],
    "types": [
      "静态"
    ],
    "copies": [
      "全员集结！攻下这座岛\n没见过这么野的生存对抗游戏"
    ],
    "dates": [
      "2026-04-06"
    ],
    "date_range": [
      "2026-04-06",
      "2026-04-06"
    ],
    "category": "对抗"
  },
  {
    "img": "imgs/image31.jpg",
    "img_file": "image31.jpg",
    "total_exposure": 1321289,
    "total_clicks": 11555,
    "avg_ctr": 0.8738,
    "max_ctr": 0.9,
    "min_ctr": 0.81,
    "invest_count": 5,
    "positions": [
      "商店轮播-全量",
      "商店轮播-定投200w"
    ],
    "types": [
      "静态"
    ],
    "copies": [
      "标题：RUST正版玩法授权\n副标：硬核生存对抗，预约抽5070",
      "RUST正版玩法授权\n9月19日登岛测试，立即报名！",
      "RUST正版玩法授权\n没见过这么野的生存对抗游戏",
      "全球顶流生存对抗游戏9月测试\nPC抢先招募，预约领限定枪皮"
    ],
    "dates": [
      "2025-07-05",
      "2025-07-12",
      "2025-07-15",
      "2025-08-09",
      "2026-03-22"
    ],
    "date_range": [
      "2025-07-05",
      "2026-03-22"
    ],
    "category": "福利"
  },
  {
    "img": "imgs/image180.jpg",
    "img_file": "image180.jpg",
    "total_exposure": 206710,
    "total_clicks": 1804,
    "avg_ctr": 0.8727,
    "max_ctr": 0.8727,
    "min_ctr": 0.8727,
    "invest_count": 1,
    "positions": [
      "商店轮播-全量"
    ],
    "types": [
      "静态+动态视频"
    ],
    "copies": [
      "没见过这么野的生存对抗游戏\n测试火热进行中，预约赢Q币"
    ],
    "dates": [
      "2026-03-06"
    ],
    "date_range": [
      "2026-03-06",
      "2026-03-06"
    ],
    "category": "趣味"
  },
  {
    "img": "imgs/image10.jpg",
    "img_file": "image10.jpg",
    "total_exposure": 3044903,
    "total_clicks": 24995,
    "avg_ctr": 0.821,
    "max_ctr": 1.19,
    "min_ctr": 0.45,
    "invest_count": 12,
    "positions": [
      "商店轮播-全量",
      "商店轮播-定投200w",
      "首帧轮播-定投100w"
    ],
    "types": [
      "静态+动态视频",
      "静态"
    ],
    "copies": [
      "RUST玩法授权，领预约豪礼\n9月19日登岛测试，立即报名！",
      "RUST正版玩法授权\n9月大规模测试，PC抢先招募中",
      "标题：RUST正版玩法授权\n副标：硬核生存对抗，预约抽5070",
      "9月登岛测试，立即报名！\nRUST玩法授权，领预约豪礼",
      "RUST正版玩法授权\n9月大规模测试 PC抢先招募中",
      "RUST正版玩法授权\n9月19日登岛测试，立即报名！"
    ],
    "dates": [
      "2025-07-05",
      "2025-07-12",
      "2025-07-15",
      "2025-07-19",
      "2025-07-23",
      "2025-08-16",
      "2025-08-22",
      "2025-08-04",
      "2025-08-06",
      "2025-08-09",
      "2025-08-11",
      "2025-08-13"
    ],
    "date_range": [
      "2025-07-05",
      "2025-08-22"
    ],
    "category": "福利"
  },
  {
    "img": "imgs/image7.jpg",
    "img_file": "image7.jpg",
    "total_exposure": 486121,
    "total_clicks": 4135,
    "avg_ctr": 0.8676,
    "max_ctr": 0.9129,
    "min_ctr": 0.79,
    "invest_count": 3,
    "positions": [
      "商店轮播-全量",
      "商店轮播-定投200w"
    ],
    "types": [
      "静态"
    ],
    "copies": [
      "标题：RUST正版玩法授权\n副标：硬核生存对抗，预约抽5070",
      "RUST正版玩法授权\n9月大规模测试 PC抢先招募中"
    ],
    "dates": [
      "2025-07-05",
      "2025-07-12",
      "2025-07-15"
    ],
    "date_range": [
      "2025-07-05",
      "2025-07-15"
    ],
    "category": "福利"
  },
  {
    "img": "imgs/image90.jpg",
    "img_file": "image90.jpg",
    "total_exposure": 1343500,
    "total_clicks": 12457,
    "avg_ctr": 0.8503,
    "max_ctr": 1.13,
    "min_ctr": 0.61,
    "invest_count": 7,
    "positions": [
      "商店轮播-定投200w",
      "商店轮播-全量",
      "首帧轮播-定投100w"
    ],
    "types": [
      "静态+动态视频"
    ],
    "copies": [
      "生存试炼，活到最后才是赢家！\n收集情报领最高188Q币",
      "生存试炼，活到最后才是赢家！\n预约领枪皮，暴击千元Q币！"
    ],
    "dates": [
      "2025-10-02",
      "2025-10-10",
      "2025-10-11",
      "2025-10-12",
      "2025-10-14",
      "2025-10-17",
      "2025-10-18"
    ],
    "date_range": [
      "2025-10-02",
      "2025-10-18"
    ],
    "category": "生存"
  },
  {
    "img": "imgs/image150.jpg",
    "img_file": "image150.jpg",
    "total_exposure": 240797,
    "total_clicks": 2028,
    "avg_ctr": 0.8422,
    "max_ctr": 0.8422,
    "min_ctr": 0.8422,
    "invest_count": 1,
    "positions": [
      "商店轮播-全量"
    ],
    "types": [
      "静态+动态视频"
    ],
    "copies": [
      "高自由度生存对抗\n预约领枪皮，赢千元Q币"
    ],
    "dates": [
      "2026-01-26"
    ],
    "date_range": [
      "2026-01-26",
      "2026-01-26"
    ],
    "category": "对抗"
  },
  {
    "img": "imgs/image84.jpg",
    "img_file": "image84.jpg",
    "total_exposure": 4705501,
    "total_clicks": 37824,
    "avg_ctr": 0.8414,
    "max_ctr": 1.06,
    "min_ctr": 0.6373,
    "invest_count": 12,
    "positions": [
      "首帧轮播-全量",
      "商店轮播-定投200w",
      "商店轮播-全量",
      "首帧轮播-定投100w"
    ],
    "types": [
      "静态+动态视频"
    ],
    "copies": [
      "打造枪械 制霸荒岛\n立即抢号试玩，预约领Q币",
      "真开放世界，顶流生存射击\n预约领限定枪皮，抽5070",
      "打造枪械 制霸荒岛\n预约领限定枪皮，抽5070"
    ],
    "dates": [
      "2025-09-21",
      "2025-09-23",
      "2025-09-25",
      "2025-09-26",
      "2025-09-27",
      "2025-09-28",
      "2025-10-02",
      "2025-10-03",
      "2025-10-04",
      "2025-10-05",
      "2025-10-06",
      "2025-10-09"
    ],
    "date_range": [
      "2025-09-21",
      "2025-10-09"
    ],
    "category": "武器"
  },
  {
    "img": "imgs/image179.jpg",
    "img_file": "image179.jpg",
    "total_exposure": 203517,
    "total_clicks": 1710,
    "avg_ctr": 0.8402,
    "max_ctr": 0.8402,
    "min_ctr": 0.8402,
    "invest_count": 1,
    "positions": [
      "商店轮播-全量"
    ],
    "types": [
      "静态+动态视频"
    ],
    "copies": [
      "全新体验，沉浸式生存对抗！\n终极测试开放中，点击立即抢号"
    ],
    "dates": [
      "2026-03-06"
    ],
    "date_range": [
      "2026-03-06",
      "2026-03-06"
    ],
    "category": "对抗"
  },
  {
    "img": "imgs/image34.jpg",
    "img_file": "image34.jpg",
    "total_exposure": 42783,
    "total_clicks": 358,
    "avg_ctr": 0.84,
    "max_ctr": 0.84,
    "min_ctr": 0.84,
    "invest_count": 1,
    "positions": [
      "首帧轮播-定投100w"
    ],
    "types": [
      "静态"
    ],
    "copies": [
      "RUST玩法授权，领预约豪礼\n9月19日登岛测试，立即报名！"
    ],
    "dates": [
      "2025-08-13"
    ],
    "date_range": [
      "2025-08-13",
      "2025-08-13"
    ],
    "category": "福利"
  },
  {
    "img": "imgs/image181.jpg",
    "img_file": "image181.jpg",
    "total_exposure": 919587,
    "total_clicks": 7437,
    "avg_ctr": 0.8398,
    "max_ctr": 0.9047,
    "min_ctr": 0.7329,
    "invest_count": 3,
    "positions": [
      "商店轮播-全量"
    ],
    "types": [
      "静态+动态视频",
      "静态"
    ],
    "copies": [
      "开放世界，射击生存对抗\n预约赢5070Ti、千元Q币"
    ],
    "dates": [
      "2026-03-06",
      "2026-03-11",
      "2026-03-17"
    ],
    "date_range": [
      "2026-03-06",
      "2026-03-17"
    ],
    "category": "对抗"
  },
  {
    "img": "imgs/image13.jpg",
    "img_file": "image13.jpg",
    "total_exposure": 1919426,
    "total_clicks": 15433,
    "avg_ctr": 0.8327,
    "max_ctr": 1.01,
    "min_ctr": 0.43,
    "invest_count": 5,
    "positions": [
      "商店轮播-全量",
      "商店轮播-定投200w"
    ],
    "types": [
      "静态"
    ],
    "copies": [
      "标题：RUST正版玩法授权\n副标：硬核生存对抗，预约抽5070",
      "RUST正版玩法授权\n9月大规模测试 PC抢先招募中",
      "全球顶流生存对抗游戏9月测试\nPC抢先招募，预约赢5070",
      "RUST正版玩法授权\n9月大规模测试，PC抢先招募中"
    ],
    "dates": [
      "2025-07-05",
      "2025-07-12",
      "2025-07-15",
      "2025-07-19",
      "2025-07-25"
    ],
    "date_range": [
      "2025-07-05",
      "2025-07-25"
    ],
    "category": "福利"
  },
  {
    "img": "imgs/image112.jpg",
    "img_file": "image112.jpg",
    "total_exposure": 10474,
    "total_clicks": 87,
    "avg_ctr": 0.83,
    "max_ctr": 0.83,
    "min_ctr": 0.83,
    "invest_count": 1,
    "positions": [
      "商店轮播-定投200w"
    ],
    "types": [
      "静态+动态视频"
    ],
    "copies": [
      "没见过这么野的生存对抗游戏\n预约领限定枪皮、千元Q币"
    ],
    "dates": [
      "2025-10-25"
    ],
    "date_range": [
      "2025-10-25",
      "2025-10-25"
    ],
    "category": "趣味"
  },
  {
    "img": "imgs/image159.jpg",
    "img_file": "image159.jpg",
    "total_exposure": 797156,
    "total_clicks": 6602,
    "avg_ctr": 0.8282,
    "max_ctr": 0.8282,
    "min_ctr": 0.8282,
    "invest_count": 1,
    "positions": [
      "首帧轮播-全量"
    ],
    "types": [
      "静态+动态视频"
    ],
    "copies": [
      "没见过这么野的生存对抗游戏\n终极测试 今日开启"
    ],
    "dates": [
      "2026-02-03"
    ],
    "date_range": [
      "2026-02-03",
      "2026-02-03"
    ],
    "category": "趣味"
  },
  {
    "img": "imgs/image89.jpg",
    "img_file": "image89.jpg",
    "total_exposure": 876636,
    "total_clicks": 8116,
    "avg_ctr": 0.8274,
    "max_ctr": 0.9422,
    "min_ctr": 0.6,
    "invest_count": 3,
    "positions": [
      "商店轮播-全量",
      "首帧轮播-定投100w"
    ],
    "types": [
      "静态+动态视频"
    ],
    "copies": [
      "全网预约突破2000万\n预约领枪皮，暴击千元Q币！",
      "全网2000万预约达成\n预约领枪皮，暴击千元Q币！"
    ],
    "dates": [
      "2025-09-28",
      "2025-10-10",
      "2025-10-11"
    ],
    "date_range": [
      "2025-09-28",
      "2025-10-11"
    ],
    "category": "生存"
  },
  {
    "img": "imgs/image101.jpg",
    "img_file": "image101.jpg",
    "total_exposure": 6292194,
    "total_clicks": 51141,
    "avg_ctr": 0.8268,
    "max_ctr": 1.2,
    "min_ctr": 0.56,
    "invest_count": 22,
    "positions": [
      "首帧轮播-全量",
      "商店轮播-定投200w",
      "商店轮播-全量",
      "首帧轮播-定投100w"
    ],
    "types": [
      "静态+动态视频"
    ],
    "copies": [
      "体验共研服诚邀精英上岛！\n预约领限定枪皮，抽千元QB",
      "登岛开测 立即抢号\n预约领枪皮，暴击千元Q币！",
      "生存对抗，随我一起登岛\n预约领枪皮，暴击千元Q币！",
      "登岛开测 立即抢号\n预约领枪皮，暴击千元Q币",
      "体验共研服诚邀精英上岛！\n预约领限定枪皮，赢千元Q币"
    ],
    "dates": [
      "2025-10-02",
      "2025-10-05",
      "2025-10-09",
      "2025-10-10",
      "2025-10-11",
      "2025-10-12",
      "2025-10-14",
      "2025-10-17",
      "2025-10-18",
      "2025-10-21",
      "2025-10-25",
      "2025-10-27",
      "2025-10-29",
      "2025-10-31",
      "2025-11-01",
      "2025-11-02",
      "2025-11-08",
      "2025-11-14",
      "2025-11-15",
      "2025-12-20",
      "2025-12-21",
      "2026-01-04"
    ],
    "date_range": [
      "2025-10-02",
      "2026-01-04"
    ],
    "category": "福利"
  },
  {
    "img": "imgs/image63.jpg",
    "img_file": "image63.jpg",
    "total_exposure": 1339511,
    "total_clicks": 11831,
    "avg_ctr": 0.8228,
    "max_ctr": 0.9184,
    "min_ctr": 0.74,
    "invest_count": 3,
    "positions": [
      "商店轮播-全量",
      "首帧轮播-全量",
      "商店轮播-定投200w"
    ],
    "types": [
      "静态+动态视频",
      "静态"
    ],
    "copies": [
      "真·开放世界，顶流生存射击\n预约领枪皮，抽京东卡、5070",
      "真·开放世界，顶流生存射击\n9月登岛测试，立即报名！"
    ],
    "dates": [
      "2025-09-04",
      "2025-09-06",
      "2025-09-07"
    ],
    "date_range": [
      "2025-09-04",
      "2025-09-07"
    ],
    "category": "探索"
  },
  {
    "img": "imgs/image87.jpg",
    "img_file": "image87.jpg",
    "total_exposure": 7820,
    "total_clicks": 64,
    "avg_ctr": 0.82,
    "max_ctr": 0.82,
    "min_ctr": 0.82,
    "invest_count": 1,
    "positions": [
      "商店轮播-定投200w"
    ],
    "types": [
      "静态+动态视频"
    ],
    "copies": [
      "登岛开测 立即抢号\n预约领枪皮，暴击千元Q币"
    ],
    "dates": [
      "2025-09-27"
    ],
    "date_range": [
      "2025-09-27",
      "2025-09-27"
    ],
    "category": "福利"
  },
  {
    "img": "imgs/image111.jpg",
    "img_file": "image111.jpg",
    "total_exposure": 9940,
    "total_clicks": 82,
    "avg_ctr": 0.82,
    "max_ctr": 0.82,
    "min_ctr": 0.82,
    "invest_count": 1,
    "positions": [
      "商店轮播-定投200w"
    ],
    "types": [
      "静态+动态视频"
    ],
    "copies": [
      "生存试炼，活到最后才是赢家！\n点击抢号试玩，预约领Q币！"
    ],
    "dates": [
      "2025-10-25"
    ],
    "date_range": [
      "2025-10-25",
      "2025-10-25"
    ],
    "category": "生存"
  },
  {
    "img": "imgs/image182.jpg",
    "img_file": "image182.jpg",
    "total_exposure": 3917,
    "total_clicks": 32,
    "avg_ctr": 0.82,
    "max_ctr": 0.82,
    "min_ctr": 0.82,
    "invest_count": 1,
    "positions": [
      "商店轮播-定投200w"
    ],
    "types": [
      "静态+动态视频"
    ],
    "copies": [
      "立即抢号，参与终极测试！\n赢5070Ti显卡、千元Q币"
    ],
    "dates": [
      "2026-03-07"
    ],
    "date_range": [
      "2026-03-07",
      "2026-03-07"
    ],
    "category": "对抗"
  },
  {
    "img": "imgs/image148.jpg",
    "img_file": "image148.jpg",
    "total_exposure": 6608670,
    "total_clicks": 53166,
    "avg_ctr": 0.8181,
    "max_ctr": 0.9679,
    "min_ctr": 0.6,
    "invest_count": 12,
    "positions": [
      "首帧轮播-全量",
      "商店轮播-全量",
      "商店轮播-定投200w"
    ],
    "types": [
      "静态+动态视频",
      "静态"
    ],
    "copies": [
      "立即抢号，参与终极测试\n来体验高自由度生存对抗",
      "高自由度生存对抗\n预约领枪皮，赢千元Q币",
      "终极测试 今日开启\n来体验高自由度生存对抗",
      "立即抢号，参与终极测试！\n高自由度生存对抗玩到爽",
      "开放世界，射击生存对抗\n立即抢号，参与终极测试！",
      "开放世界 生存对抗\n立即抢号，参与终极测试！",
      "终极测试开放中，点击立即抢号\n预约赢显卡，抽千元Q币",
      "开放世界，射击生存对抗\n预约赢5070Ti、千元Q币",
      "原汁原味、生存对抗游戏\n立即抢号，参与终极测试！"
    ],
    "dates": [
      "2026-01-25",
      "2026-02-03",
      "2026-02-05",
      "2026-02-06",
      "2026-02-07",
      "2026-02-13",
      "2026-02-17",
      "2026-02-20",
      "2026-02-27",
      "2026-03-03",
      "2026-03-06",
      "2026-03-08"
    ],
    "date_range": [
      "2026-01-25",
      "2026-03-08"
    ],
    "category": "对抗"
  },
  {
    "img": "imgs/image122.jpg",
    "img_file": "image122.jpg",
    "total_exposure": 14852240,
    "total_clicks": 122247,
    "avg_ctr": 0.8173,
    "max_ctr": 1.45,
    "min_ctr": 0.36,
    "invest_count": 53,
    "positions": [
      "首帧轮播-全量",
      "商店轮播-定投200w",
      "商店轮播-全量",
      "首帧轮播-定投100w"
    ],
    "types": [
      "静态+动态视频",
      "静态"
    ],
    "copies": [
      "体验共研服招募开启，诚邀上岛！\n预约领枪皮，抽千元Q币",
      "体验共研服招募开启，诚邀上岛！\n预约领枪皮，最高188Q币",
      "开放世界 生存对抗\n立即抢号，参与终极测试！",
      "荒岛求生 探索开放大世界\n预约领限定枪皮、千元Q币",
      "探索开放世界，体验生存对抗\n立即抢号，得终极测试资格！",
      "立即抢号，参与终极测试！\n高自由度生存对抗玩到爽",
      "开放世界，射击生存对抗\n预约赢5070Ti、千元Q币",
      "立即抢号，参与终极测试！\n赢5070Ti显卡、千元Q币",
      "享受建造和掠夺的快乐\n立即抢号，得终极测试资格！",
      "立即抢号，参与终极测试！\n开放世界，射击生存对抗",
      "体验共研服招募开启，诚邀上岛！\n预约领枪皮，抽5070显卡",
      "终极测试招募，立即报名！\n预约领枪皮，赢千元Q币",
      "掠夺资源 建造你的专属领地\n共研服招募开启，立即报名！",
      "登岛开测 立即抢号\n预约领枪皮，暴击千元Q币",
      "开放世界，射击生存对抗\n立即抢号，参与终极测试！",
      "高自由度生存对抗\n立即抢号，参与终极测试！",
      "开放世界，射击生存对抗\n立即参与测试，赢千元Q币",
      "终极测试 今日开启\n探索开放世界，体验生存对抗",
      "搭建领地，开启生存对抗\n立即参与测试，赢千元Q币",
      "终极测试开放中，点击立即抢号\n预约赢5070Ti、千元Q币",
      "终极测试开放中，点击立即抢号\n预约赢显卡，抽千元Q币",
      "搭建领地，开启生存对抗\n立即抢号，参与终极测试！",
      "开放世界 建造专属领地\n预约领限定枪皮、抽Q币",
      "开放世界 建造专属领地\n预约领枪皮，抽千元Q币"
    ],
    "dates": [
      "2025-09-28",
      "2025-10-05",
      "2025-10-10",
      "2025-10-11",
      "2025-10-14",
      "2025-10-17",
      "2025-10-18",
      "2025-10-21",
      "2025-10-25",
      "2025-10-27",
      "2025-10-29",
      "2025-10-31",
      "2025-11-01",
      "2025-11-02",
      "2025-11-08",
      "2025-11-14",
      "2025-11-15",
      "2025-11-21",
      "2025-11-28",
      "2025-12-12",
      "2025-12-13",
      "2025-12-19",
      "2025-12-20",
      "2025-12-21",
      "2025-12-26",
      "2025-12-28",
      "2026-01-03",
      "2026-01-07",
      "2026-01-08",
      "2026-01-09",
      "2026-01-26",
      "2026-01-29",
      "2026-01-30",
      "2026-02-03",
      "2026-02-04",
      "2026-02-05",
      "2026-02-06",
      "2026-02-07",
      "2026-02-08",
      "2026-02-13",
      "2026-02-14",
      "2026-02-17",
      "2026-02-20",
      "2026-02-27",
      "2026-03-03",
      "2026-03-05",
      "2026-03-06",
      "2026-03-07",
      "2026-03-08",
      "2026-03-09",
      "2026-03-11",
      "2026-03-12",
      "2026-03-17"
    ],
    "date_range": [
      "2025-09-28",
      "2026-03-17"
    ],
    "category": "福利"
  },
  {
    "img": "imgs/image109.jpg",
    "img_file": "image109.jpg",
    "total_exposure": 10715693,
    "total_clicks": 86111,
    "avg_ctr": 0.8054,
    "max_ctr": 1.45,
    "min_ctr": 0.4969,
    "invest_count": 32,
    "positions": [
      "首帧轮播-全量",
      "商店轮播-定投200w",
      "商店轮播-全量",
      "首帧轮播-定投100w"
    ],
    "types": [
      "静态+动态视频",
      "静态"
    ],
    "copies": [
      "体验共研服招募开启，诚邀上岛！\n预约领枪皮，抽千元Q币",
      "终极测试 今日开启\n立即抢号下载，抢先一步登岛",
      "终极测试 福利不停\n立即抢号，预约赢千元Q币",
      "开放世界 生存对抗\n预约领限定枪皮、千元Q币",
      "立即抢号，参与终极测试\n预约赢显卡，抽千元Q币",
      "终极测试开放中，点击立即抢号\n赢5070Ti显卡、千元Q币",
      "立即抢号，得终极测试资格！\n预约领枪皮，赢千元Q币",
      "开放世界，射击生存对抗\n预约赢5070Ti、千元Q币",
      "立即抢号，参与终极测试\n预约领枪皮，赢千元Q币",
      "体验共研服招募开启，诚邀上岛！\n预约领枪皮，抽5070显卡",
      "立即抢号，参与终极测试\n没见过这么野的生存对抗游戏",
      "立即抢号，参与终极测试\n来体验高自由度生存对抗",
      "终极测试招募，立即报名！\n预约领枪皮，赢千元Q币",
      "没见过这么野的生存对抗游戏\n立即参与测试，赢千元Q币",
      "登岛开测，点击抢号试玩\n预约领限定枪皮、千元Q币",
      "终极测试 超燃对抗\n立即抢号，解锁你的生存玩法！",
      "高自由度生存对抗玩到爽\n分享测试资格，邀友一起上岛！",
      "没见过这么野的生存对抗游戏\n预约领限定枪皮、千元Q币",
      "荒岛求生 探索开放大世界\n预约领枪皮，抽千元Q币"
    ],
    "dates": [
      "2025-10-21",
      "2025-10-25",
      "2025-10-27",
      "2025-10-29",
      "2025-10-31",
      "2025-11-01",
      "2025-11-02",
      "2025-11-08",
      "2025-11-14",
      "2025-11-15",
      "2025-12-20",
      "2025-12-21",
      "2026-01-03",
      "2026-01-07",
      "2026-01-08",
      "2026-01-09",
      "2026-01-25",
      "2026-01-26",
      "2026-01-29",
      "2026-01-30",
      "2026-02-03",
      "2026-02-04",
      "2026-02-05",
      "2026-02-06",
      "2026-02-07",
      "2026-02-08",
      "2026-02-13",
      "2026-02-14",
      "2026-02-17",
      "2026-02-20",
      "2026-02-27",
      "2026-03-06"
    ],
    "date_range": [
      "2025-10-21",
      "2026-03-06"
    ],
    "category": "福利"
  },
  {
    "img": "imgs/image121.jpg",
    "img_file": "image121.jpg",
    "total_exposure": 309956,
    "total_clicks": 2486,
    "avg_ctr": 0.802,
    "max_ctr": 0.802,
    "min_ctr": 0.802,
    "invest_count": 1,
    "positions": [
      "商店轮播-全量"
    ],
    "types": [
      "静态+动态视频"
    ],
    "copies": [
      "开放世界 生存对抗\n预约领枪皮，暴击千元Q币！"
    ],
    "dates": [
      "2025-11-21"
    ],
    "date_range": [
      "2025-11-21",
      "2025-11-21"
    ],
    "category": "对抗"
  },
  {
    "img": "imgs/image138.jpg",
    "img_file": "image138.jpg",
    "total_exposure": 9611185,
    "total_clicks": 77741,
    "avg_ctr": 0.8009,
    "max_ctr": 1.27,
    "min_ctr": 0.29,
    "invest_count": 39,
    "positions": [
      "首帧轮播-全量",
      "商店轮播-全量",
      "商店轮播-定投200w",
      "首帧轮播-定投100w"
    ],
    "types": [
      "静态+动态视频",
      "静态"
    ],
    "copies": [
      "立即抢号下载，抢先一步登岛\n终极测试 今日开启",
      "登岛开测 立即抢号\n预约领枪皮，暴击千元Q币！",
      "生存对抗 荒岛称霸\n终极测试招募，立即报名！",
      "立即抢号，参与终极测试\n来体验高自由度生存对抗",
      "登岛开测，点击抢号试玩\n收集情报领最高188Q币！",
      "登岛开测 立即抢号\n预约领枪皮，暴击千元Q币",
      "生存对抗，随我一起登岛\n立即抢号，得终极测试资格！",
      "体验共研服诚邀精英上岛！\n预约领限定枪皮，赢千元Q币",
      "开放世界 生存对抗\n点亮称号领最高388Q币",
      "没见过这么野的生存对抗游戏\n立即抢号，参与终极测试！",
      "生存对抗 荒岛争霸\n点亮称号抽最高388Q币",
      "生存对抗，谁能笑到最后\n共研服招募开启，立即登岛！",
      "生存对抗 荒岛争霸\n探索据点领最高188Q币",
      "生存试炼，活到最后才是赢家！\n收集情报领最高188Q币",
      "终极测试 福利不停\n资格分享开启，邀友一起上岛！",
      "生存试炼，活到最后才是赢家！\n探索据点领最高188Q币",
      "登岛开测，点击抢号试玩\n预约领枪皮，暴击千元Q币！"
    ],
    "dates": [
      "2025-10-04",
      "2025-10-06",
      "2025-10-10",
      "2025-10-11",
      "2025-10-12",
      "2025-10-14",
      "2025-10-17",
      "2025-10-18",
      "2025-10-21",
      "2025-10-25",
      "2025-10-27",
      "2025-10-29",
      "2025-10-31",
      "2025-11-01",
      "2025-11-02",
      "2025-11-08",
      "2025-11-14",
      "2025-11-15",
      "2025-11-21",
      "2025-11-22",
      "2025-11-28",
      "2025-12-12",
      "2025-12-13",
      "2025-12-20",
      "2025-12-26",
      "2025-12-28",
      "2026-01-04",
      "2026-01-07",
      "2026-01-08",
      "2026-01-09",
      "2026-01-25",
      "2026-01-26",
      "2026-01-29",
      "2026-01-30",
      "2026-02-03",
      "2026-02-04",
      "2026-02-05",
      "2026-02-06",
      "2026-02-07"
    ],
    "date_range": [
      "2025-10-04",
      "2026-02-07"
    ],
    "category": "对抗"
  },
  {
    "img": "imgs/image61.jpg",
    "img_file": "image61.jpg",
    "total_exposure": 377272,
    "total_clicks": 3019,
    "avg_ctr": 0.8,
    "max_ctr": 0.8,
    "min_ctr": 0.8,
    "invest_count": 1,
    "positions": [
      "商店轮播-全量"
    ],
    "types": [
      "静态"
    ],
    "copies": [
      "掠夺资源 荒岛称霸\n9月登岛测试，立即报名！"
    ],
    "dates": [
      "2025-09-03"
    ],
    "date_range": [
      "2025-09-03",
      "2025-09-03"
    ],
    "category": "对抗"
  },
  {
    "img": "imgs/image113.jpg",
    "img_file": "image113.jpg",
    "total_exposure": 13417,
    "total_clicks": 108,
    "avg_ctr": 0.8,
    "max_ctr": 0.8,
    "min_ctr": 0.8,
    "invest_count": 1,
    "positions": [
      "商店轮播-定投200w"
    ],
    "types": [
      "静态+动态视频"
    ],
    "copies": [
      "生存试炼，活到最后才是赢家！\n点击抢号试玩，预约领Q币！"
    ],
    "dates": [
      "2025-10-27"
    ],
    "date_range": [
      "2025-10-27",
      "2025-10-27"
    ],
    "category": "生存"
  },
  {
    "img": "imgs/image176.jpg",
    "img_file": "image176.jpg",
    "total_exposure": 257713,
    "total_clicks": 2034,
    "avg_ctr": 0.7893,
    "max_ctr": 0.7893,
    "min_ctr": 0.7893,
    "invest_count": 1,
    "positions": [
      "商店轮播-全量"
    ],
    "types": [
      "静态+动态视频"
    ],
    "copies": [
      "终极测试 超燃对抗\n预约赢50系显卡、千元Q币"
    ],
    "dates": [
      "2026-03-03"
    ],
    "date_range": [
      "2026-03-03",
      "2026-03-03"
    ],
    "category": "对抗"
  },
  {
    "img": "imgs/image94.jpg",
    "img_file": "image94.jpg",
    "total_exposure": 934521,
    "total_clicks": 8434,
    "avg_ctr": 0.7891,
    "max_ctr": 0.9484,
    "min_ctr": 0.54,
    "invest_count": 7,
    "positions": [
      "商店轮播-全量",
      "商店轮播-定投200w",
      "首帧轮播-定投100w"
    ],
    "types": [
      "静态+动态视频"
    ],
    "copies": [
      "没见过这么野的生存对抗游戏\n收集情报领最高188Q币！",
      "生存对抗，活到最后才是赢家\n收集情报领最高188Q币！",
      "全网2000万预约达成\n点击抢号试玩，预约领Q币！",
      "全网2000万预约达成\n立即抢号试玩，预约领Q币！"
    ],
    "dates": [
      "2025-10-04",
      "2025-10-10",
      "2025-10-11",
      "2025-10-12",
      "2025-10-14",
      "2025-10-17",
      "2025-10-18"
    ],
    "date_range": [
      "2025-10-04",
      "2025-10-18"
    ],
    "category": "趣味"
  },
  {
    "img": "imgs/image102.jpg",
    "img_file": "image102.jpg",
    "total_exposure": 4664365,
    "total_clicks": 37823,
    "avg_ctr": 0.7853,
    "max_ctr": 1.24,
    "min_ctr": 0.37,
    "invest_count": 26,
    "positions": [
      "商店轮播-定投200w",
      "商店轮播-全量",
      "首帧轮播-定投100w"
    ],
    "types": [
      "静态+动态视频",
      "静态"
    ],
    "copies": [
      "生存对抗，谁能笑到最后\n共研服招募开启，立即登岛",
      "没见过这么野的生存对抗游戏\n收集情报领最高188Q币！",
      "高自由度生存对抗\n终极测试招募，立即报名！",
      "没见过这么野的生存对抗游戏\n预约赢5070Ti、千元Q币",
      "立即抢号，参与终极测试！\n来体验高自由度生存对抗",
      "生存对抗，谁能笑到最后\n预约领枪皮，赢千元Q币",
      "直面生存考验，体验原始博弈\n预约领限定枪皮、千元Q币",
      "没见过这么野的生存对抗游戏\n预约领限定枪皮、千元Q币",
      "立即抢号，参与终极测试！\n高自由度生存对抗玩到爽",
      "开放世界 荒岛求生\n预约领限定枪皮、千元Q币",
      "没见过这么野的生存对抗游戏\n点击抢号试玩，预约领Q币！",
      "生存对抗，谁能笑到最后\n共研服招募开启，立即登岛！"
    ],
    "dates": [
      "2025-10-12",
      "2025-10-14",
      "2025-10-17",
      "2025-10-18",
      "2025-10-21",
      "2025-10-31",
      "2025-11-02",
      "2025-11-08",
      "2025-11-14",
      "2025-11-15",
      "2025-11-21",
      "2025-11-22",
      "2025-11-28",
      "2025-12-12",
      "2025-12-13",
      "2025-12-18",
      "2025-12-19",
      "2025-12-26",
      "2025-12-27",
      "2026-01-03",
      "2026-01-07",
      "2026-01-08",
      "2026-01-09",
      "2026-02-05",
      "2026-02-06",
      "2026-03-12"
    ],
    "date_range": [
      "2025-10-12",
      "2026-03-12"
    ],
    "category": "对抗"
  },
  {
    "img": "imgs/image72.png",
    "img_file": "image72.png",
    "total_exposure": 265323,
    "total_clicks": 2062,
    "avg_ctr": 0.78,
    "max_ctr": 0.78,
    "min_ctr": 0.78,
    "invest_count": 1,
    "positions": [
      "商店轮播-全量"
    ],
    "types": [
      "静态+动态视频"
    ],
    "copies": [
      "荒岛求生 探索开放大世界\n预约领枪皮，抽京东卡、5070"
    ],
    "dates": [
      "2025-09-09"
    ],
    "date_range": [
      "2025-09-09",
      "2025-09-09"
    ],
    "category": "探索"
  },
  {
    "img": "imgs/image119.jpg",
    "img_file": "image119.jpg",
    "total_exposure": 1738499,
    "total_clicks": 13714,
    "avg_ctr": 0.7793,
    "max_ctr": 0.957,
    "min_ctr": 0.63,
    "invest_count": 9,
    "positions": [
      "商店轮播-定投200w",
      "商店轮播-全量"
    ],
    "types": [
      "静态+动态视频"
    ],
    "copies": [
      "开放世界 生存对抗\n探索据点领最高188Q币",
      "RUST正版玩法，激烈生存对决\n领预约好礼，暴击千元Q币",
      "开放世界 生存对抗\n点亮称号抽最高388Q币"
    ],
    "dates": [
      "2025-11-08",
      "2025-11-14",
      "2025-11-15",
      "2025-11-21",
      "2025-11-22",
      "2025-11-28",
      "2025-12-12",
      "2025-12-27",
      "2026-01-04"
    ],
    "date_range": [
      "2025-11-08",
      "2026-01-04"
    ],
    "category": "探索"
  },
  {
    "img": "imgs/image86.jpg",
    "img_file": "image86.jpg",
    "total_exposure": 476218,
    "total_clicks": 4319,
    "avg_ctr": 0.771,
    "max_ctr": 1.0,
    "min_ctr": 0.56,
    "invest_count": 4,
    "positions": [
      "商店轮播-全量",
      "商店轮播-定投200w",
      "首帧轮播-定投100w"
    ],
    "types": [
      "静态+动态视频"
    ],
    "copies": [
      "搭建领地 攻防博弈\n收集情报领最高188Q币"
    ],
    "dates": [
      "2025-09-27",
      "2025-10-10",
      "2025-10-11",
      "2025-10-12"
    ],
    "date_range": [
      "2025-09-27",
      "2025-10-12"
    ],
    "category": "建造"
  },
  {
    "img": "imgs/image117.jpg",
    "img_file": "image117.jpg",
    "total_exposure": 4621303,
    "total_clicks": 34386,
    "avg_ctr": 0.7652,
    "max_ctr": 1.58,
    "min_ctr": 0.497,
    "invest_count": 22,
    "positions": [
      "首帧轮播-全量",
      "商店轮播-定投200w",
      "商店轮播-全量"
    ],
    "types": [
      "静态+动态视频",
      "静态"
    ],
    "copies": [
      "高自由度生存对抗\n终极测试招募，立即报名！",
      "高自由度生存对抗\n立即抢号，得终极测试资格！",
      "高自由度生存对抗\n预约领枪皮，赢千元Q币",
      "终极测试开放中，点击立即抢号\n开放世界，射击生存对抗",
      "全新体验，沉浸式生存对抗！\n终极测试开放中，点击立即抢号",
      "丛林法则 生存对抗\n预约领枪皮，暴击千元Q币！",
      "生存法则 由你定义\n预约领枪皮，抽50系显卡",
      "生存对抗 荒岛称霸\n预约领枪皮，赢千元Q币",
      "没见过这么野的生存对抗游戏\n共研服招募开启，立即报名！",
      "生存法则 由你定义\n立即抢号，终极测试今日开启",
      "生存法则，由你定义\n共研服招募开启，立即登岛！",
      "RUST正版玩法，激烈生存对决\n领预约好礼，暴击千元Q币",
      "生存对抗，谁能笑到最后\n共研服招募开启，立即登岛！"
    ],
    "dates": [
      "2025-11-08",
      "2025-11-14",
      "2025-11-15",
      "2025-11-21",
      "2025-11-22",
      "2025-11-28",
      "2025-12-13",
      "2025-12-18",
      "2025-12-19",
      "2025-12-21",
      "2025-12-27",
      "2026-01-03",
      "2026-01-07",
      "2026-01-08",
      "2026-01-09",
      "2026-01-25",
      "2026-01-26",
      "2026-01-29",
      "2026-01-30",
      "2026-02-03",
      "2026-02-14",
      "2026-03-05"
    ],
    "date_range": [
      "2025-11-08",
      "2026-03-05"
    ],
    "category": "对抗"
  },
  {
    "img": "imgs/image118.jpg",
    "img_file": "image118.jpg",
    "total_exposure": 1371207,
    "total_clicks": 11176,
    "avg_ctr": 0.7649,
    "max_ctr": 0.956,
    "min_ctr": 0.43,
    "invest_count": 10,
    "positions": [
      "商店轮播-定投200w",
      "商店轮播-全量"
    ],
    "types": [
      "静态+动态视频"
    ],
    "copies": [
      "开放世界 生存对抗\n共研服招募开启，立即登岛！",
      "没见过这么野的生存对抗游戏\n探索据点领最高188Q币",
      "没见过这么野的生存对抗游戏\n集结好友暴击千元QB"
    ],
    "dates": [
      "2025-11-08",
      "2025-11-14",
      "2025-11-15",
      "2025-11-21",
      "2025-11-22",
      "2025-11-28",
      "2025-12-12",
      "2025-12-13",
      "2025-12-26",
      "2025-12-28"
    ],
    "date_range": [
      "2025-11-08",
      "2025-12-28"
    ],
    "category": "探索"
  },
  {
    "img": "imgs/image54.png",
    "img_file": "image54.png",
    "total_exposure": 1712841,
    "total_clicks": 13027,
    "avg_ctr": 0.761,
    "max_ctr": 0.84,
    "min_ctr": 0.69,
    "invest_count": 5,
    "positions": [
      "商店轮播-全量"
    ],
    "types": [
      "静态",
      "静态+动态视频"
    ],
    "copies": [
      "人性试炼场，活到最后才是赢家\n9月19日登岛测试，立即报名！",
      "人性试炼场，活到最后才是赢家\n登岛测试，立即报名！",
      "RUST玩法授权，领预约豪礼\n9月19日登岛测试，立即报名！"
    ],
    "dates": [
      "2025-08-24",
      "2025-08-29",
      "2025-08-30",
      "2025-08-16",
      "2025-08-22"
    ],
    "date_range": [
      "2025-08-16",
      "2025-08-30"
    ],
    "category": "生存"
  },
  {
    "img": "imgs/image1.jpg",
    "img_file": "image1.jpg",
    "total_exposure": 1003900,
    "total_clicks": 6109,
    "avg_ctr": 0.7603,
    "max_ctr": 0.9811,
    "min_ctr": 0.38,
    "invest_count": 4,
    "positions": [
      "商店轮播-全量",
      "商店轮播-定投200w"
    ],
    "types": [
      "静态"
    ],
    "copies": [
      "RUST正版玩法授权\n9月大规模测试 PC抢先招募中",
      "标题：全球顶流生存对抗游戏\n副标：RUST玩法授权，立即预约",
      "全球顶流生存对抗游戏9月测试\nPC抢先招募，预约赢5070"
    ],
    "dates": [
      "2025-07-05",
      "2025-07-12",
      "2025-07-15",
      "2025-07-19"
    ],
    "date_range": [
      "2025-07-05",
      "2025-07-19"
    ],
    "category": "福利"
  },
  {
    "img": "imgs/image70.jpg",
    "img_file": "image70.jpg",
    "total_exposure": 382023,
    "total_clicks": 2904,
    "avg_ctr": 0.76,
    "max_ctr": 0.76,
    "min_ctr": 0.76,
    "invest_count": 1,
    "positions": [
      "商店轮播-全量"
    ],
    "types": [
      "静态+动态视频"
    ],
    "copies": [
      "这次你当猎物还是猎人？\n9月登岛测试，立即报名！"
    ],
    "dates": [
      "2025-09-07"
    ],
    "date_range": [
      "2025-09-07",
      "2025-09-07"
    ],
    "category": "对抗"
  },
  {
    "img": "imgs/image71.jpg",
    "img_file": "image71.jpg",
    "total_exposure": 266687,
    "total_clicks": 2020,
    "avg_ctr": 0.76,
    "max_ctr": 0.76,
    "min_ctr": 0.76,
    "invest_count": 1,
    "positions": [
      "商店轮播-全量"
    ],
    "types": [
      "静态+动态视频"
    ],
    "copies": [
      "生存试炼，活到最后才是赢家！\n9月登岛测试，立即报名"
    ],
    "dates": [
      "2025-09-09"
    ],
    "date_range": [
      "2025-09-09",
      "2025-09-09"
    ],
    "category": "生存"
  },
  {
    "img": "imgs/image127.jpg",
    "img_file": "image127.jpg",
    "total_exposure": 6468188,
    "total_clicks": 50664,
    "avg_ctr": 0.7522,
    "max_ctr": 1.0131,
    "min_ctr": 0.5,
    "invest_count": 23,
    "positions": [
      "首帧轮播-全量",
      "商店轮播-全量",
      "商店轮播-定投200w",
      "首帧轮播-定投100w"
    ],
    "types": [
      "静态+动态视频",
      "静态"
    ],
    "copies": [
      "活下去，为生存而战\n终极测试招募，立即报名！",
      "终极测试 火热开启\n预约领枪皮，赢千元Q币",
      "终极测试开放中，点击立即抢号\n开放世界，射击生存对抗",
      "立即抢号，参与终极测试\n没见过这么野的生存对抗游戏",
      "享受建造和掠夺的快乐\n共研服招募开启，一起登岛！",
      "高自由度生存对抗玩到爽\n分享测试资格，邀友一起上岛！",
      "没见过这么野的生存对抗游戏\n测试火热进行中，预约赢Q币",
      "终极测试 今日开启\n生存对抗 荒岛称霸",
      "没见过这么野的生存对抗游戏\n测试火热开启，预约赢Q币",
      "开放世界，射击生存对抗\n预约赢5070Ti、千元Q币",
      "生存对抗 荒岛称霸\n预约领枪皮，赢千元Q币",
      "没见过这么野的生存对抗游戏\n立即抢号，参与终极测试！",
      "终极测试 超燃对抗\n预约赢50系显卡、千元Q币",
      "享受建造和掠夺的快乐\n共研服招募开启，立即登岛！",
      "没见过这么野的生存对抗游戏\n抢号参与测试，预约赢Q币",
      "享受建造和掠夺的快乐\n终极测试招募，立即报名"
    ],
    "dates": [
      "2025-12-18",
      "2025-12-19",
      "2026-01-04",
      "2026-01-08",
      "2026-01-09",
      "2026-01-25",
      "2026-01-29",
      "2026-01-30",
      "2026-02-03",
      "2026-02-04",
      "2026-02-05",
      "2026-02-06",
      "2026-02-07",
      "2026-02-08",
      "2026-02-13",
      "2026-02-14",
      "2026-02-17",
      "2026-02-20",
      "2026-03-03",
      "2026-03-05",
      "2026-03-06",
      "2026-03-07",
      "2026-03-09"
    ],
    "date_range": [
      "2025-12-18",
      "2026-03-09"
    ],
    "category": "生存"
  },
  {
    "img": "imgs/image42.jpg",
    "img_file": "image42.jpg",
    "total_exposure": 339231,
    "total_clicks": 2535,
    "avg_ctr": 0.75,
    "max_ctr": 0.75,
    "min_ctr": 0.75,
    "invest_count": 1,
    "positions": [
      "商店轮播-全量"
    ],
    "types": [
      "静态+动态视频"
    ],
    "copies": [
      "RUST玩法授权，领预约豪礼\n9月19日登岛测试，立即报名！"
    ],
    "dates": [
      "2025-08-16"
    ],
    "date_range": [
      "2025-08-16",
      "2025-08-16"
    ],
    "category": "福利"
  },
  {
    "img": "imgs/image47.png",
    "img_file": "image47.png",
    "total_exposure": 146542,
    "total_clicks": 1097,
    "avg_ctr": 0.75,
    "max_ctr": 0.75,
    "min_ctr": 0.75,
    "invest_count": 1,
    "positions": [
      "商店轮播-全量"
    ],
    "types": [
      "静态"
    ],
    "copies": [
      "RUST玩法授权，领预约豪礼\n9月19日登岛测试，立即报名！"
    ],
    "dates": [
      "2025-08-22"
    ],
    "date_range": [
      "2025-08-22",
      "2025-08-22"
    ],
    "category": "福利"
  },
  {
    "img": "imgs/image73.png",
    "img_file": "image73.png",
    "total_exposure": 266528,
    "total_clicks": 2008,
    "avg_ctr": 0.75,
    "max_ctr": 0.75,
    "min_ctr": 0.75,
    "invest_count": 1,
    "positions": [
      "商店轮播-全量"
    ],
    "types": [
      "静态+动态视频"
    ],
    "copies": [
      "这次你当猎物还是猎人？\n9月登岛测试，立即报名！"
    ],
    "dates": [
      "2025-09-09"
    ],
    "date_range": [
      "2025-09-09",
      "2025-09-09"
    ],
    "category": "对抗"
  },
  {
    "img": "imgs/image74.png",
    "img_file": "image74.png",
    "total_exposure": 261866,
    "total_clicks": 1960,
    "avg_ctr": 0.75,
    "max_ctr": 0.75,
    "min_ctr": 0.75,
    "invest_count": 1,
    "positions": [
      "商店轮播-全量"
    ],
    "types": [
      "静态+动态视频"
    ],
    "copies": [
      "真·开放世界，顶流生存射击\n预约领限定枪皮，抽5070"
    ],
    "dates": [
      "2025-09-09"
    ],
    "date_range": [
      "2025-09-09",
      "2025-09-09"
    ],
    "category": "探索"
  },
  {
    "img": "imgs/image120.jpg",
    "img_file": "image120.jpg",
    "total_exposure": 7224319,
    "total_clicks": 52309,
    "avg_ctr": 0.7432,
    "max_ctr": 1.13,
    "min_ctr": 0.55,
    "invest_count": 24,
    "positions": [
      "首帧轮播-全量",
      "商店轮播-全量",
      "商店轮播-定投200w"
    ],
    "types": [
      "静态+动态视频",
      "静态"
    ],
    "copies": [
      "终极测试 限时抢号\n开放世界，射击生存对抗",
      "体验共研服诚邀精英上岛！\n预约领限定枪皮，抽千元QB",
      "从零开始：拾荒、建造、称王\n预约领限定枪皮、千元Q币",
      "终极测试 火热开启\n预约领枪皮，赢千元Q币",
      "终极测试开放中，点击立即抢号\n开放世界，射击生存对抗",
      "立即抢号，得终极测试资格！\n点亮称号领最高388Q币",
      "从零开始：拾荒、建造、称王\n共研服招募开启，立即登岛！",
      "生存对抗，随我一起登岛\n立即抢号，开启预下载",
      "生存对抗新体验\n立即抢号，参与终极测试！",
      "从零开始：拾荒、建造、称王\n预约领枪皮，赢千元Q币",
      "开放世界 生存对抗\n立即抢号，参与终极测试！",
      "终极测试招募，立即报名！\n点亮称号领最高388Q币",
      "荒岛求生 探索开放大世界\n预约领枪皮，暴击千元Q币！",
      "开放世界 生存对抗\n领预约好礼，暴击千元Q币"
    ],
    "dates": [
      "2025-11-15",
      "2025-11-21",
      "2025-11-22",
      "2025-11-28",
      "2025-12-12",
      "2025-12-13",
      "2025-12-18",
      "2025-12-19",
      "2025-12-20",
      "2025-12-26",
      "2025-12-27",
      "2026-01-03",
      "2026-01-07",
      "2026-01-08",
      "2026-01-09",
      "2026-01-25",
      "2026-01-26",
      "2026-02-03",
      "2026-02-04",
      "2026-02-05",
      "2026-02-06",
      "2026-02-17",
      "2026-02-20",
      "2026-02-27"
    ],
    "date_range": [
      "2025-11-15",
      "2026-02-27"
    ],
    "category": "建造"
  },
  {
    "img": "imgs/image36.jpg",
    "img_file": "image36.jpg",
    "total_exposure": 40760,
    "total_clicks": 300,
    "avg_ctr": 0.74,
    "max_ctr": 0.74,
    "min_ctr": 0.74,
    "invest_count": 1,
    "positions": [
      "首帧轮播-定投100w"
    ],
    "types": [
      "静态"
    ],
    "copies": [
      "RUST玩法授权，领预约豪礼\n9月19日登岛测试，立即报名！"
    ],
    "dates": [
      "2025-08-13"
    ],
    "date_range": [
      "2025-08-13",
      "2025-08-13"
    ],
    "category": "福利"
  },
  {
    "img": "imgs/image43.jpg",
    "img_file": "image43.jpg",
    "total_exposure": 334925,
    "total_clicks": 2470,
    "avg_ctr": 0.74,
    "max_ctr": 0.74,
    "min_ctr": 0.74,
    "invest_count": 1,
    "positions": [
      "商店轮播-全量"
    ],
    "types": [
      "静态+动态视频"
    ],
    "copies": [
      "RUST玩法授权，领预约豪礼\n9月19日登岛测试，立即报名！"
    ],
    "dates": [
      "2025-08-16"
    ],
    "date_range": [
      "2025-08-16",
      "2025-08-16"
    ],
    "category": "福利"
  },
  {
    "img": "imgs/image59.jpg",
    "img_file": "image59.jpg",
    "total_exposure": 361739,
    "total_clicks": 2686,
    "avg_ctr": 0.74,
    "max_ctr": 0.74,
    "min_ctr": 0.74,
    "invest_count": 1,
    "positions": [
      "商店轮播-全量"
    ],
    "types": [
      "静态"
    ],
    "copies": [
      "丛林法则 生存试炼\n预约领限定枪皮，抽5070"
    ],
    "dates": [
      "2025-09-03"
    ],
    "date_range": [
      "2025-09-03",
      "2025-09-03"
    ],
    "category": "生存"
  },
  {
    "img": "imgs/image174.jpg",
    "img_file": "image174.jpg",
    "total_exposure": 1285646,
    "total_clicks": 9762,
    "avg_ctr": 0.7344,
    "max_ctr": 0.7743,
    "min_ctr": 0.6946,
    "invest_count": 2,
    "positions": [
      "首帧轮播-全量",
      "商店轮播-全量"
    ],
    "types": [
      "静态"
    ],
    "copies": [
      "没见过这么野的生存对抗游戏\n测试火热开启，预约赢Q币",
      "没见过这么野的生存对抗游戏\n测试火热开启，预约赢显卡"
    ],
    "dates": [
      "2026-02-17",
      "2026-02-20"
    ],
    "date_range": [
      "2026-02-17",
      "2026-02-20"
    ],
    "category": "趣味"
  },
  {
    "img": "imgs/image45.png",
    "img_file": "image45.png",
    "total_exposure": 984356,
    "total_clicks": 7256,
    "avg_ctr": 0.7337,
    "max_ctr": 0.79,
    "min_ctr": 0.6712,
    "invest_count": 3,
    "positions": [
      "商店轮播-全量"
    ],
    "types": [
      "静态"
    ],
    "copies": [
      "丛林法则，生存试炼，绝境突围\n9月19日登岛测试，立即报名！",
      "丛林法则，生存试炼，绝境突围\n登岛测试，立即报名！",
      "RUST玩法授权，领预约豪礼\n9月19日登岛测试，立即报名！"
    ],
    "dates": [
      "2025-08-22",
      "2025-08-24",
      "2025-08-29"
    ],
    "date_range": [
      "2025-08-22",
      "2025-08-29"
    ],
    "category": "生存"
  },
  {
    "img": "imgs/image114.jpg",
    "img_file": "image114.jpg",
    "total_exposure": 1884885,
    "total_clicks": 14818,
    "avg_ctr": 0.7322,
    "max_ctr": 0.9602,
    "min_ctr": 0.4,
    "invest_count": 8,
    "positions": [
      "商店轮播-定投200w",
      "商店轮播-全量"
    ],
    "types": [
      "静态+动态视频"
    ],
    "copies": [
      "体验共研服诚邀精英上岛！\n预约领限定枪皮，抽千元QB",
      "兄弟，这个家没你得散！\n共研服招募开启，立即登岛！",
      "开放世界 生存对抗\n预约领枪皮，暴击千元Q币！"
    ],
    "dates": [
      "2025-10-31",
      "2025-11-02",
      "2025-11-08",
      "2025-11-14",
      "2025-11-15",
      "2025-12-18",
      "2025-12-19",
      "2025-12-21"
    ],
    "date_range": [
      "2025-10-31",
      "2025-12-21"
    ],
    "category": "趣味"
  },
  {
    "img": "imgs/image48.jpg",
    "img_file": "image48.jpg",
    "total_exposure": 900026,
    "total_clicks": 6965,
    "avg_ctr": 0.774,
    "max_ctr": 0.78,
    "min_ctr": 0.61,
    "invest_count": 4,
    "positions": [
      "商店轮播-全量",
      "首帧轮播-定投100w"
    ],
    "types": [
      "静态",
      "静态+动态视频"
    ],
    "copies": [
      "开放世界，生存射击【搜打拆】\n9月19日登岛测试，立即报名！",
      "开放世界，生存对抗【搜打拆】\n预约领限定枪皮，抽5070",
      "RUST玩法授权，领预约豪礼\n9月19日登岛测试，立即报名！",
      "掠夺资源 荒岛称霸\n9月登岛测试，立即报名！"
    ],
    "dates": [
      "2025-08-22",
      "2025-08-24",
      "2025-08-29",
      "2025-09-07"
    ],
    "date_range": [
      "2025-08-22",
      "2025-09-07"
    ],
    "category": "对抗"
  },
  {
    "img": "imgs/image139.jpg",
    "img_file": "image139.jpg",
    "total_exposure": 1292035,
    "total_clicks": 8370,
    "avg_ctr": 0.7127,
    "max_ctr": 0.86,
    "min_ctr": 0.561,
    "invest_count": 4,
    "positions": [
      "首帧轮播-全量",
      "商店轮播-定投200w",
      "商店轮播-全量"
    ],
    "types": [
      "静态+动态视频"
    ],
    "copies": [
      "没见过这么野的生存对抗游戏\n立即抢号，得终极测试资格！",
      "没见过这么野的生存对抗游戏\n终极测试招募，立即报名！"
    ],
    "dates": [
      "2026-01-08",
      "2026-01-09",
      "2026-01-25",
      "2026-01-26"
    ],
    "date_range": [
      "2026-01-08",
      "2026-01-26"
    ],
    "category": "趣味"
  },
  {
    "img": "imgs/image56.jpg",
    "img_file": "image56.jpg",
    "total_exposure": 429891,
    "total_clicks": 3516,
    "avg_ctr": 0.818,
    "max_ctr": 0.71,
    "min_ctr": 0.71,
    "invest_count": 3,
    "positions": [
      "商店轮播-全量",
      "商店轮播-定投200w",
      "首帧轮播-定投100w"
    ],
    "types": [
      "静态",
      "静态+动态视频"
    ],
    "copies": [
      "丛林法则，生存试炼，绝境突围\n登岛测试，立即报名！",
      "丛林法则 生存试炼\n9月登岛测试，立即报名！",
      "丛林法则 生存试炼\n预约领限定枪皮，抽5070"
    ],
    "dates": [
      "2025-08-30",
      "2025-09-06",
      "2025-09-07"
    ],
    "date_range": [
      "2025-08-30",
      "2025-09-07"
    ],
    "category": "生存"
  },
  {
    "img": "imgs/image49.png",
    "img_file": "image49.png",
    "total_exposure": 1589334,
    "total_clicks": 12206,
    "avg_ctr": 0.768,
    "max_ctr": 0.8,
    "min_ctr": 0.6,
    "invest_count": 5,
    "positions": [
      "商店轮播-全量"
    ],
    "types": [
      "静态"
    ],
    "copies": [
      "开放世界【搜打拆】\n预约领枪皮，抽京东卡、5070",
      "开放世界【搜打拆】，预约领枪皮\n9月19日登岛测试，立即报名！",
      "RUST玩法授权，领预约豪礼\n9月19日登岛测试，立即报名！",
      "RUST正版玩法授权\n9月19日登岛测试，立即报名！"
    ],
    "dates": [
      "2025-08-22",
      "2025-08-24",
      "2025-08-29",
      "2025-08-30",
      "2025-08-09"
    ],
    "date_range": [
      "2025-08-09",
      "2025-08-30"
    ],
    "category": "对抗"
  },
  {
    "img": "imgs/image116.jpg",
    "img_file": "image116.jpg",
    "total_exposure": 795432,
    "total_clicks": 5374,
    "avg_ctr": 0.676,
    "max_ctr": 0.9096,
    "min_ctr": 0.56,
    "invest_count": 6,
    "positions": [
      "商店轮播-全量",
      "商店轮播-定投200w",
      "首帧轮播-定投100w"
    ],
    "types": [
      "静态+动态视频"
    ],
    "copies": [
      "没见过这么野的生存对抗游戏\n预约领枪皮，暴击千元Q币！",
      "掠夺资源 建造你的专属领地\n共研服招募开启，立即报名！",
      "没见过这么野的生存对抗游戏\n集结好友暴击千元Q币"
    ],
    "dates": [
      "2025-11-01",
      "2025-11-22",
      "2025-11-28",
      "2025-12-18",
      "2025-12-27",
      "2026-01-04"
    ],
    "date_range": [
      "2025-11-01",
      "2026-01-04"
    ],
    "category": "建造"
  },
  {
    "img": "imgs/image50.png",
    "img_file": "image50.png",
    "total_exposure": 883362,
    "total_clicks": 6652,
    "avg_ctr": 0.753,
    "max_ctr": 0.78,
    "min_ctr": 0.57,
    "invest_count": 4,
    "positions": [
      "商店轮播-全量",
      "首帧轮播-定投100w"
    ],
    "types": [
      "静态",
      "静态+动态视频"
    ],
    "copies": [
      "这次你当猎物还是猎人？\n登岛测试，立即报名！",
      "这次你当猎物还是猎人？\n9月19日登岛测试，立即报名！",
      "RUST玩法授权，领预约豪礼\n9月19日登岛测试，立即报名！",
      "真•开放世界生存对抗游戏\n预约领限定枪皮，抽5070"
    ],
    "dates": [
      "2025-08-22",
      "2025-08-24",
      "2025-08-29",
      "2025-09-07"
    ],
    "date_range": [
      "2025-08-22",
      "2025-09-07"
    ],
    "category": "对抗"
  },
  {
    "img": "imgs/image58.jpg",
    "img_file": "image58.jpg",
    "total_exposure": 335440,
    "total_clicks": 2317,
    "avg_ctr": 0.69,
    "max_ctr": 0.69,
    "min_ctr": 0.69,
    "invest_count": 1,
    "positions": [
      "商店轮播-全量"
    ],
    "types": [
      "静态"
    ],
    "copies": [
      "开放世界，生存对抗【搜打拆】\n预约领限定枪皮，抽5070"
    ],
    "dates": [
      "2025-08-30"
    ],
    "date_range": [
      "2025-08-30",
      "2025-08-30"
    ],
    "category": "对抗"
  },
  {
    "img": "imgs/image82.png",
    "img_file": "image82.png",
    "total_exposure": 377519,
    "total_clicks": 2601,
    "avg_ctr": 0.69,
    "max_ctr": 0.69,
    "min_ctr": 0.69,
    "invest_count": 1,
    "positions": [
      "商店轮播-全量"
    ],
    "types": [
      "静态+动态视频"
    ],
    "copies": [
      "真开放世界，顶流生存射击\n预约领枪皮，抽京东卡、5070"
    ],
    "dates": [
      "2025-09-20"
    ],
    "date_range": [
      "2025-09-20",
      "2025-09-20"
    ],
    "category": "探索"
  },
  {
    "img": "imgs/image123.jpg",
    "img_file": "image123.jpg",
    "total_exposure": 301087,
    "total_clicks": 2152,
    "avg_ctr": 0.6886,
    "max_ctr": 0.77,
    "min_ctr": 0.53,
    "invest_count": 4,
    "positions": [
      "商店轮播-定投200w",
      "商店轮播-全量"
    ],
    "types": [
      "静态+动态视频"
    ],
    "copies": [
      "掠夺资源 从零打造\n预约领限定枪皮、千元Q币",
      "开放世界 荒岛求生\n预约领限定枪皮、千元Q币"
    ],
    "dates": [
      "2025-12-12",
      "2025-12-13",
      "2025-12-26",
      "2025-12-28"
    ],
    "date_range": [
      "2025-12-12",
      "2025-12-28"
    ],
    "category": "建造"
  },
  {
    "img": "imgs/image64.jpg",
    "img_file": "image64.jpg",
    "total_exposure": 821191,
    "total_clicks": 5501,
    "avg_ctr": 0.6699,
    "max_ctr": 0.6699,
    "min_ctr": 0.6699,
    "invest_count": 1,
    "positions": [
      "首帧轮播-全量"
    ],
    "types": [
      "静态"
    ],
    "copies": [
      "搭建领地 攻防博弈\n预约领枪皮，抽京东卡、5070"
    ],
    "dates": [
      "2025-09-04"
    ],
    "date_range": [
      "2025-09-04",
      "2025-09-04"
    ],
    "category": "建造"
  },
  {
    "img": "imgs/image129.jpg",
    "img_file": "image129.jpg",
    "total_exposure": 2134999,
    "total_clicks": 13964,
    "avg_ctr": 0.6629,
    "max_ctr": 0.8272,
    "min_ctr": 0.5308,
    "invest_count": 6,
    "positions": [
      "首帧轮播-全量",
      "商店轮播-全量",
      "商店轮播-定投200w"
    ],
    "types": [
      "静态+动态视频"
    ],
    "copies": [
      "终极测试招募，立即报名！\n预约领枪皮，抽50系显卡",
      "没见过这么野的生存对抗游戏\n点亮称号领最高388Q币",
      "生存对抗 荒岛争霸\n共研服招募开启，立即登岛！"
    ],
    "dates": [
      "2025-12-20",
      "2025-12-21",
      "2026-01-03",
      "2026-01-07",
      "2026-01-08",
      "2026-01-09"
    ],
    "date_range": [
      "2025-12-20",
      "2026-01-09"
    ],
    "category": "对抗"
  },
  {
    "img": "imgs/image83.png",
    "img_file": "image83.png",
    "total_exposure": 372370,
    "total_clicks": 2460,
    "avg_ctr": 0.66,
    "max_ctr": 0.66,
    "min_ctr": 0.66,
    "invest_count": 1,
    "positions": [
      "商店轮播-全量"
    ],
    "types": [
      "静态+动态视频"
    ],
    "copies": [
      "搭建领地 攻防博弈\n预约领枪皮，抽京东卡、5070"
    ],
    "dates": [
      "2025-09-20"
    ],
    "date_range": [
      "2025-09-20",
      "2025-09-20"
    ],
    "category": "建造"
  },
  {
    "img": "imgs/image93.jpg",
    "img_file": "image93.jpg",
    "total_exposure": 917278,
    "total_clicks": 6023,
    "avg_ctr": 0.6566,
    "max_ctr": 0.6566,
    "min_ctr": 0.6566,
    "invest_count": 1,
    "positions": [
      "首帧轮播-全量"
    ],
    "types": [
      "静态+动态视频"
    ],
    "copies": [
      "登岛开测 立即抢号\n预约领枪皮，暴击千元Q币！"
    ],
    "dates": [
      "2025-10-03"
    ],
    "date_range": [
      "2025-10-03",
      "2025-10-03"
    ],
    "category": "福利"
  },
  {
    "img": "imgs/image185.jpg",
    "img_file": "image185.jpg",
    "total_exposure": 909387,
    "total_clicks": 5961,
    "avg_ctr": 0.6555,
    "max_ctr": 0.6555,
    "min_ctr": 0.6555,
    "invest_count": 1,
    "positions": [
      "首帧轮播-全量"
    ],
    "types": [
      "静态+动态视频"
    ],
    "copies": [
      "终极测试 超燃对抗\n预约赢50系显卡、千元Q币"
    ],
    "dates": [
      "2026-03-08"
    ],
    "date_range": [
      "2026-03-08",
      "2026-03-08"
    ],
    "category": "对抗"
  },
  {
    "img": "imgs/image92.jpg",
    "img_file": "image92.jpg",
    "total_exposure": 922186,
    "total_clicks": 6017,
    "avg_ctr": 0.6525,
    "max_ctr": 0.6525,
    "min_ctr": 0.6525,
    "invest_count": 1,
    "positions": [
      "首帧轮播-全量"
    ],
    "types": [
      "静态+动态视频"
    ],
    "copies": [
      "生存试炼，随我一起登岛！\n收集情报领最高188Q币"
    ],
    "dates": [
      "2025-10-03"
    ],
    "date_range": [
      "2025-10-03",
      "2025-10-03"
    ],
    "category": "生存"
  },
  {
    "img": "imgs/image62.jpg",
    "img_file": "image62.jpg",
    "total_exposure": 802760,
    "total_clicks": 5223,
    "avg_ctr": 0.6506,
    "max_ctr": 0.6506,
    "min_ctr": 0.6506,
    "invest_count": 1,
    "positions": [
      "首帧轮播-全量"
    ],
    "types": [
      "静态"
    ],
    "copies": [
      "丛林法则 生存试炼\n预约领限定枪皮，抽5070"
    ],
    "dates": [
      "2025-09-04"
    ],
    "date_range": [
      "2025-09-04",
      "2025-09-04"
    ],
    "category": "生存"
  },
  {
    "img": "imgs/image178.jpg",
    "img_file": "image178.jpg",
    "total_exposure": 49729,
    "total_clicks": 332,
    "avg_ctr": 0.65,
    "max_ctr": 0.67,
    "min_ctr": 0.63,
    "invest_count": 2,
    "positions": [
      "商店轮播-定投200w"
    ],
    "types": [
      "静态+动态视频"
    ],
    "copies": [
      "开放世界，射击生存对抗\n预约赢5070Ti、千元Q币",
      "开放世界，射击生存对抗\n立即抢号，参与终极测试！"
    ],
    "dates": [
      "2026-03-05",
      "2026-03-09"
    ],
    "date_range": [
      "2026-03-05",
      "2026-03-09"
    ],
    "category": "对抗"
  },
  {
    "img": "imgs/image184.jpg",
    "img_file": "image184.jpg",
    "total_exposure": 898834,
    "total_clicks": 5823,
    "avg_ctr": 0.6478,
    "max_ctr": 0.6478,
    "min_ctr": 0.6478,
    "invest_count": 1,
    "positions": [
      "首帧轮播-全量"
    ],
    "types": [
      "静态+动态视频"
    ],
    "copies": [
      "终极测试 超燃对抗\n预约赢50系显卡、千元Q币"
    ],
    "dates": [
      "2026-03-08"
    ],
    "date_range": [
      "2026-03-08",
      "2026-03-08"
    ],
    "category": "对抗"
  },
  {
    "img": "imgs/image151.jpg",
    "img_file": "image151.jpg",
    "total_exposure": 15010,
    "total_clicks": 95,
    "avg_ctr": 0.639,
    "max_ctr": 0.66,
    "min_ctr": 0.6179,
    "invest_count": 2,
    "positions": [
      "商店轮播-定投200w"
    ],
    "types": [
      "静态+动态视频"
    ],
    "copies": [
      "没见过这么野的生存对抗游戏\n预约领枪皮，赢千元Q币"
    ],
    "dates": [
      "2026-01-29",
      "2026-01-30"
    ],
    "date_range": [
      "2026-01-29",
      "2026-01-30"
    ],
    "category": "趣味"
  },
  {
    "img": "imgs/image85.jpg",
    "img_file": "image85.jpg",
    "total_exposure": 55106,
    "total_clicks": 341,
    "avg_ctr": 0.62,
    "max_ctr": 0.62,
    "min_ctr": 0.62,
    "invest_count": 1,
    "positions": [
      "首帧轮播-定投100w"
    ],
    "types": [
      "静态+动态视频"
    ],
    "copies": [
      "开放世界 生存对抗\n预约领枪皮，抽京东卡、5070"
    ],
    "dates": [
      "2025-09-22"
    ],
    "date_range": [
      "2025-09-22",
      "2025-09-22"
    ],
    "category": "探索"
  },
  {
    "img": "imgs/image124.jpg",
    "img_file": "image124.jpg",
    "total_exposure": 284507,
    "total_clicks": 2033,
    "avg_ctr": 0.6184,
    "max_ctr": 0.7168,
    "min_ctr": 0.52,
    "invest_count": 2,
    "positions": [
      "商店轮播-定投200w",
      "商店轮播-全量"
    ],
    "types": [
      "静态+动态视频"
    ],
    "copies": [
      "睁开眼，直面生存考验！\n预约领限定枪皮、抽Q币"
    ],
    "dates": [
      "2025-12-12",
      "2025-12-13"
    ],
    "date_range": [
      "2025-12-12",
      "2025-12-13"
    ],
    "category": "生存"
  },
  {
    "img": "imgs/image104.jpg",
    "img_file": "image104.jpg",
    "total_exposure": 12667,
    "total_clicks": 77,
    "avg_ctr": 0.61,
    "max_ctr": 0.61,
    "min_ctr": 0.61,
    "invest_count": 1,
    "positions": [
      "首帧轮播-定投100w"
    ],
    "types": [
      "静态+动态视频"
    ],
    "copies": [
      "从零建造 自由随心\n点击抢号试玩，预约领Q币"
    ],
    "dates": [
      "2025-10-12"
    ],
    "date_range": [
      "2025-10-12",
      "2025-10-12"
    ],
    "category": "建造"
  },
  {
    "img": "imgs/image171.jpg",
    "img_file": "image171.jpg",
    "total_exposure": 39159,
    "total_clicks": 239,
    "avg_ctr": 0.61,
    "max_ctr": 0.61,
    "min_ctr": 0.61,
    "invest_count": 1,
    "positions": [
      "首帧轮播-定投100w"
    ],
    "types": [
      "静态"
    ],
    "copies": [
      "立即抢号，参与终极测试\n预约领枪皮，赢5070Ti显卡"
    ],
    "dates": [
      "2026-02-08"
    ],
    "date_range": [
      "2026-02-08",
      "2026-02-08"
    ],
    "category": "对抗"
  },
  {
    "img": "imgs/image126.jpg",
    "img_file": "image126.jpg",
    "total_exposure": 1522885,
    "total_clicks": 8654,
    "avg_ctr": 0.6085,
    "max_ctr": 0.76,
    "min_ctr": 0.5506,
    "invest_count": 5,
    "positions": [
      "首帧轮播-全量",
      "商店轮播-全量",
      "商店轮播-定投200w"
    ],
    "types": [
      "静态+动态视频"
    ],
    "copies": [
      "生存对抗 荒岛争霸\n预约领枪皮，赢千元Q币",
      "生存对抗 荒岛争霸\n共研服招募开启，立即登岛！"
    ],
    "dates": [
      "2025-12-18",
      "2025-12-19",
      "2025-12-20",
      "2025-12-21",
      "2025-12-28"
    ],
    "date_range": [
      "2025-12-18",
      "2025-12-28"
    ],
    "category": "对抗"
  },
  {
    "img": "imgs/image186.jpg",
    "img_file": "image186.jpg",
    "total_exposure": 873554,
    "total_clicks": 5300,
    "avg_ctr": 0.6067,
    "max_ctr": 0.6067,
    "min_ctr": 0.6067,
    "invest_count": 1,
    "positions": [
      "首帧轮播-全量"
    ],
    "types": [
      "静态+动态视频"
    ],
    "copies": [
      "没见过这么野的生存对抗游戏\n测试火热进行中，预约赢Q币"
    ],
    "dates": [
      "2026-03-08"
    ],
    "date_range": [
      "2026-03-08",
      "2026-03-08"
    ],
    "category": "趣味"
  },
  {
    "img": "imgs/image177.jpg",
    "img_file": "image177.jpg",
    "total_exposure": 44400,
    "total_clicks": 250,
    "avg_ctr": 0.56,
    "max_ctr": 0.56,
    "min_ctr": 0.56,
    "invest_count": 1,
    "positions": [
      "商店轮播-定投200w"
    ],
    "types": [
      "静态+动态视频"
    ],
    "copies": [
      "终极测试 超燃对抗\n预约赢50系显卡、千元Q币"
    ],
    "dates": [
      "2026-03-05"
    ],
    "date_range": [
      "2026-03-05",
      "2026-03-05"
    ],
    "category": "对抗"
  },
  {
    "img": "imgs/image103.jpg",
    "img_file": "image103.jpg",
    "total_exposure": 12200,
    "total_clicks": 67,
    "avg_ctr": 0.55,
    "max_ctr": 0.55,
    "min_ctr": 0.55,
    "invest_count": 1,
    "positions": [
      "首帧轮播-定投100w"
    ],
    "types": [
      "静态+动态视频"
    ],
    "copies": [
      "开放世界 荒岛求生\n预约领枪皮，暴击千元Q币！"
    ],
    "dates": [
      "2025-10-12"
    ],
    "date_range": [
      "2025-10-12",
      "2025-10-12"
    ],
    "category": "探索"
  },
  {
    "img": "imgs/image172.jpg",
    "img_file": "image172.jpg",
    "total_exposure": 36646,
    "total_clicks": 196,
    "avg_ctr": 0.53,
    "max_ctr": 0.53,
    "min_ctr": 0.53,
    "invest_count": 1,
    "positions": [
      "首帧轮播-定投100w"
    ],
    "types": [
      "静态"
    ],
    "copies": [
      "没见过这么野的生存对抗游戏\n立即抢号，参与终极测试！"
    ],
    "dates": [
      "2026-02-08"
    ],
    "date_range": [
      "2026-02-08",
      "2026-02-08"
    ],
    "category": "趣味"
  },
  {
    "img": "imgs/image26.png",
    "img_file": "image26.png",
    "total_exposure": 341353,
    "total_clicks": 1463,
    "avg_ctr": 0.43,
    "max_ctr": 0.43,
    "min_ctr": 0.43,
    "invest_count": 1,
    "positions": [
      "商店轮播-全量"
    ],
    "types": [
      "静态"
    ],
    "copies": [
      "全球顶流生存对抗游戏9月测试\nPC抢先招募，预约赢5070"
    ],
    "dates": [
      "2025-08-04"
    ],
    "date_range": [
      "2025-08-04",
      "2025-08-04"
    ],
    "category": "福利"
  },
  {
    "img": "imgs/image23.png",
    "img_file": "image23.png",
    "total_exposure": 336169,
    "total_clicks": 1372,
    "avg_ctr": 0.41,
    "max_ctr": 0.41,
    "min_ctr": 0.41,
    "invest_count": 1,
    "positions": [
      "商店轮播-全量"
    ],
    "types": [
      "静态"
    ],
    "copies": [
      "RUST正版玩法授权\n9月大规模测试，PC抢先招募中"
    ],
    "dates": [
      "2025-08-04"
    ],
    "date_range": [
      "2025-08-04",
      "2025-08-04"
    ],
    "category": "福利"
  },
  {
    "img": "imgs/image27.png",
    "img_file": "image27.png",
    "total_exposure": 370475,
    "total_clicks": 1676,
    "avg_ctr": 0.452,
    "max_ctr": 0.4,
    "min_ctr": 0.4,
    "invest_count": 2,
    "positions": [
      "商店轮播-全量",
      "首帧轮播-定投100w"
    ],
    "types": [
      "静态"
    ],
    "copies": [
      "全球顶流生存对抗游戏9月测试\nPC抢先招募，预约赢5070",
      "RUST玩法授权，领预约豪礼\n9月19日登岛测试，立即报名！"
    ],
    "dates": [
      "2025-08-04",
      "2025-08-13"
    ],
    "date_range": [
      "2025-08-04",
      "2025-08-13"
    ],
    "category": "福利"
  },
  {
    "img": "imgs/image22.png",
    "img_file": "image22.png",
    "total_exposure": 330802,
    "total_clicks": 1287,
    "avg_ctr": 0.39,
    "max_ctr": 0.39,
    "min_ctr": 0.39,
    "invest_count": 1,
    "positions": [
      "商店轮播-全量"
    ],
    "types": [
      "静态"
    ],
    "copies": [
      "RUST正版玩法授权\n9月大规模测试，PC抢先招募中"
    ],
    "dates": [
      "2025-08-04"
    ],
    "date_range": [
      "2025-08-04",
      "2025-08-04"
    ],
    "category": "福利"
  }
]